Workbook

Sheet 2026
B1: Expense | C1: Income | D1: Net Profit | E1: Transport | F1: Living | G1: Bill | H1: Groceries | I1: Dine | J1: RMIT | K1: Mortgage | L1: Childcare | M1: One off item
B2: =SUM(E2:L2) -> 0 | C2: =SUM(C3:C14) -> 0 | D2: =SUM(B2,C2) -> 0 | E2: =SUM(E15:E1014) -> 0 | F2: =SUM(F15:F1014) -> 0 | G2: =SUM(G15:G1014) -> 0 | H2: =SUM(H15:H1014) -> 0 | I2: =SUM(I16:I1014) -> 0 | J2: =SUM(J15:J1014) -> 0 | K2: =SUM(K15:K1014) -> 0 | L2: =SUM(L15:L1014) -> 0 | M2: =SUM(M15:M1014) -> 0
A3: 46023
A4: 46054
A5: 46082
A6: 46113
A7: 46143
A8: 46174 | AF8: 2
A9: 46204
A10: 46235
A11: 46266
A12: 46296
A13: 46327
A14: 46357
A15: 46023
A16: 46024
A17: 46025
A18: 46026 | AF18: 11222
A19: 46027
A20: 46028
A21: 46029
A22: 46030
A23: 46031
A24: 46032
A25: 46033
A26: 46034
A27: 46035
A28: 46036
A29: 46037
A30: 46038
... A151: 46159
A152: 46160 | AF152: `1!!@ Ｚ～````重 １１`２重：Ｌ；Ｌ／Ｌ；｝
A153: 46161
A154: 46162
A155: 46163
A156: 46164
A157: 46165
A158: 46166
A159: 46167
A160: 46168
A161: 46169
A162: 46170
A163: 46171
A164: 46172
... A379: 46387

Sheet 2026_income
B1: interest | C1: Will | D1: Yan | E1: Salary Package
B2: =sum(B3:B1000) -> 0 | C2: =sum(C3:C1000) -> 94572.94 | D2: =sum(D3:D1000) -> 11859.25 | E2: =sum(E3:E1000) -> 9507.84
A3: JAN | C3: =3515.61*2 -> 7031.22 | D3: =28.7*2+2122.98 -> 2180.38 | F3: =sum(B3:E3) -> 9211.6
A4: FEB | C4: =3515.61+3647.34 -> 7162.95 | D4: =sum(28.7*2,301.56,487.72) -> 846.68 | F4: =sum(B4:E4) -> 8009.63
A5: MAR | C5: =3515.61*2 -> 7031.22 | D5: =384.17+28.7+101.95+28.7+203.91 -> 747.43 | E5: 768.34 | F5: =sum(B5:E5) -> 8546.99
A6: APR | C6: =3515.61*3 -> 10546.83 | D6: =28.7*2+152.63 -> 210.03 | E6: =sum(454.85,113.71,123.47) -> 692.03 | F6: =sum(B6:E6) -> 11448.89
A7: MAY | C7: =3515.61*2 -> 7031.22 | D7: =28.7*3+101.95*2+210.03 -> 500.03 | E7: =384.17+791.4 -> 1175.57 | F7: =sum(B7:E7) -> 8706.82
A8: JUN | C8: =3641.58*2 -> 7283.16 | D8: =28.7*2+157.22 -> 214.62 | E8: 607.37 | F8: =sum(B8:E8) -> 8105.15
A9: JUL | C9: =3641.5*2 -> 7283 | D9: =157.22+12.3 -> 169.52 | E9: 607.37 | F9: =sum(B9:E9) -> 8059.89
A10: AUG | C10: =3641.58*2 -> 7283.16 | D10: =43.88+4+2826.84+164.24+69.58 -> 3108.54 | E10: 635.45 | F10: =sum(B10:E10) -> 11027.15
A11: SEP | C11: =3641.58*2 -> 7283.16 | D11: =342.67+171.34 -> 514.01 | E11: =1342.35+661.64 -> 2003.99 | F11: =sum(B11:E11) -> 9801.16
A12: OCT | C12: =3641.6*3 -> 10924.8 | D12: =181.41+170.76+171.34 -> 523.51 | E12: =701.95+661.64+661.64 -> 2025.23 | F12: =sum(B12:E12) -> 13473.54
A13: NOV | C13: =3641.58*2 -> 7283.16 | D13: =355.36+1322.59 -> 1677.95 | E13: 992.49 | F13: =sum(B13:E13) -> 9953.6
A14: DEC | C14: =4697.65+3731.41 -> 8429.06 | D14: 1166.55 | F14: =sum(B14:E14) -> 9595.61

Sheet 2025
B1: Expense | C1: Income | D1: Net Profit | E1: Transport | F1: Living | G1: Bill | H1: Groceries | I1: Dine | J1: RMIT | K1: Mortgage | L1: Childcare | M1: One off item
B2: =SUM(E2:L2) -> -99854.86 | C2: =SUM(C3:C14) -> 115940.03 | D2: =SUM(B2,C2) -> 16085.17 | E2: =SUM(E15:E1014) -> -2057.74 | F2: =SUM(F15:F1014) -> -12794.98 | G2: =SUM(G15:G1014) -> -16539.02 | H2: =SUM(H15:H1014) -> -15830.92 | I2: =SUM(I16:I1014) -> -5750.71 | J2: =SUM(J15:J1014) -> -10038 | K2: =SUM(K15:K1014) -> -32137 | L2: =SUM(L15:L1014) -> -4706.49 | M2: =SUM(M15:M1014) -> 13395.67
A3: 45658 | B3: =SUM(E3:L3) -> -11256.84 | C3: ='2025_income'!F3 -> 9211.6 | D3: =SUM(B3,C3) -> -2045.24 | E3: =sum(E15:E45) -> -30 | F3: =sum(F15:F45) -> -378.82 | G3: =sum(G15:G45) -> -417.78 | H3: =sum(H15:H45) -> -1829.55 | I3: =sum(I16:I45) -> -598.35 | J3: =sum(J15:J45) -> -5000 | K3: =sum(K15:K45) -> -2641 | L3: =sum(L15:L45) -> -361.34 | M3: =sum(M15:M45) -> 0
A4: 45689 | B4: =SUM(E4:L4) -> -6822.81 | C4: ='2025_income'!F4 -> 8009.63 | D4: =SUM(B4,C4) -> 1186.82 | E4: =SUM(E46:E73) -> -30 | F4: =SUM(F46:F73) -> -606.55 | G4: =SUM(G46:G73) -> -1538.9 | H4: =SUM(H46:H73) -> -1308.15 | I4: =SUM(I46:I73) -> -376.93 | J4: =SUM(J46:J73) -> -38 | K4: =SUM(K46:K73) -> -2641 | L4: =SUM(L46:L73) -> -283.28 | M4: =SUM(M46:M73) -> 0
A5: 45717 | B5: =SUM(E5:L5) -> -12781.32 | C5: ='2025_income'!F5 -> 8546.99 | D5: =SUM(B5,C5) -> -4234.33 | E5: =sum(E74:E104) -> 0 | F5: =sum(F74:F104) -> -114.92 | G5: =sum(G74:G104) -> -3222.92 | H5: =sum(H74:H104) -> -1230.51 | I5: =sum(I74:I104) -> -269.92 | J5: =sum(J74:J104) -> -5000 | K5: =sum(K74:K104) -> -2641 | L5: =sum(L74:L104) -> -302.05 | M5: =sum(M74:M104) -> 0
A6: 45748 | B6: =SUM(E6:L6) -> -6219.8 | C6: ='2025_income'!F6 -> 11448.89 | D6: =SUM(B6,C6) -> 5229.09 | E6: =sum(E105:E134) -> -5.6 | F6: =sum(F105:F134) -> -615.04 | G6: =sum(G105:G134) -> -707.91 | H6: =sum(H105:H134) -> -1554.5 | I6: =sum(I105:I134) -> -412.47 | J6: =sum(J105:J134) -> 0 | K6: =sum(K105:K134) -> -2641 | L6: =sum(L105:L134) -> -283.28 | M6: =sum(M105:M134) -> 0
A7: 45778 | B7: =SUM(E7:L7) -> -6466.07 | C7: ='2025_income'!F7 -> 8706.82 | D7: =SUM(B7,C7) -> 2240.75 | E7: =sum(E135:E165) -> -90 | F7: =sum(F135:F165) -> -386.37 | G7: =sum(G135:G165) -> -1044.16 | H7: =sum(H135:H165) -> -1451.82 | I7: =sum(I135:I165) -> -529.44 | J7: =sum(J135:J165) -> 0 | K7: =sum(K135:K165) -> -2641 | L7: =sum(L135:L165) -> -323.28 | M7: =sum(M135:M165) -> 0
A8: 45809 | B8: =SUM(E8:L8) -> -8757.38 | C8: ='2025_income'!F8 -> 8105.15 | D8: =SUM(B8,C8) -> -652.23 | E8: =sum(E166:E195) -> -20 | F8: =sum(F166:F195) -> -2442.25 | G8: =sum(G166:G195) -> -1709.96 | H8: =sum(H166:H195) -> -1289.41 | I8: =sum(I166:I195) -> -371.48 | J8: =sum(J166:J195) -> 0 | K8: =sum(K166:K195) -> -2641 | L8: =sum(L166:L195) -> -283.28 | M8: =sum(M166:M195) -> 0 | AF8: 2
A9: 45839 | B9: =SUM(E9:L9) -> -7019.42 | C9: ='2025_income'!F9 -> 8059.89 | D9: =SUM(B9,C9) -> 1040.47 | E9: =sum(E196:E226) -> -20 | F9: =sum(F196:F226) -> -881.4 | G9: =sum(G196:G226) -> -1062.7 | H9: =sum(H196:H226) -> -1374.21 | I9: =sum(I196:I226) -> -587.86 | J9: =sum(J196:J226) -> 0 | K9: =sum(K196:K226) -> -2651 | L9: =sum(L196:L226) -> -442.25 | M9: =sum(M196:M226) -> 0
A10: 45870 | B10: =SUM(E10:L10) -> -5931.69 | C10: ='2025_income'!F10 -> 11027.15 | D10: =SUM(B10,C10) -> 5095.46 | E10: =sum(E227:E257) -> 0 | F10: =sum(F227:F257) -> 2078.14 | G10: =sum(G227:G257) -> -1929.22 | H10: =sum(H227:H257) -> -1432.11 | I10: =sum(I227:I257) -> -664.85 | J10: =sum(J227:J257) -> 0 | K10: =sum(K227:K257) -> -3410 | L10: =sum(L227:L257) -> -573.65 | M10: =sum(M227:M257) -> 0
A11: 45901 | B11: =SUM(E11:L11) -> -12784.76 | C11: ='2025_income'!F11 -> 9801.16 | D11: =SUM(B11,C11) -> -2983.6 | E11: =SUM(E258:E287) -> -14 | F11: =SUM(F258:F287) -> -5594.8 | G11: =SUM(G258:G287) -> -1229.71 | H11: =SUM(H258:H287) -> -1296.25 | I11: =SUM(I258:I287) -> -709.88 | J11: =SUM(J258:J287) -> 0 | K11: =SUM(K258:K287) -> -3410 | L11: =SUM(L258:L287) -> -530.12 | M11: =SUM(M258:M287) -> 0
A12: 45931 | B12: =SUM(E12:L12) -> -7441.09 | C12: ='2025_income'!F12 -> 13473.54 | D12: =SUM(B12,C12) -> 6032.45 | E12: =SUM(E288:E318) -> -236.04 | F12: =SUM(F288:F318) -> -1210.76 | G12: =SUM(G288:G318) -> -1082.18 | H12: =SUM(H288:H318) -> -809.11 | I12: =SUM(I288:I318) -> -116.2 | J12: =SUM(J288:J318) -> 0 | K12: =SUM(K288:K318) -> -3410 | L12: =SUM(L288:L318) -> -576.8 | M12: =SUM(M288:M318) -> 0
A13: 45962 | B13: =SUM(E13:L13) -> -9227.8 | C13: ='2025_income'!F13 -> 9953.6 | D13: =SUM(B13,C13) -> 725.8 | E13: =SUM(E319:E348) -> -1597.13 | F13: =SUM(F319:F348) -> -1114.86 | G13: =SUM(G319:G348) -> -1061.37 | H13: =SUM(H319:H348) -> -978.5 | I13: =SUM(I319:I348) -> -562.08 | J13: =SUM(J319:J348) -> 0 | K13: =SUM(K319:K348) -> -3410 | L13: =SUM(L319:L348) -> -503.86 | M13: =SUM(M319:M348) -> 6550
A14: 45992 | B14: =SUM(E14:L14) -> -5067.88 | C14: ='2025_income'!F14 -> 9595.61 | D14: =SUM(B14,C14) -> 4527.73 | E14: =SUM(E349:E379) -> -14.97 | F14: =SUM(F349:F379) -> -1527.35 | G14: =SUM(G349:G378) -> -1532.21 | H14: =SUM(H349:H378) -> -1276.8 | I14: =SUM(I349:I378) -> -473.25 | J14: =SUM(J349:J379) -> 0 | K14: =SUM(K349:K379) -> 0 | L14: =SUM(L349:L379) -> -243.3 | M14: =SUM(M349:M379) -> 6845.67
A15: 45658 | G15: -9.99 | H15: =-10.5-37.44-13.8 -> -61.74 | I15: -18.78
A16: 45659 | H16: =-112.32-13.72-23.41 -> -149.45 | I16: -14.72
A17: 45660 | E17: -10 | F17: -48 | H17: =-57.29-13.85-25.35-46.95-18.29-56.39-26.29 -> -244.41 | I17: =-56.01-5.57-5.05 -> -66.63 | L17: -58.32
A18: 45661 | H18: =-6.23-31.76 -> -37.99 | I18: -14.72 | AF18: 11222
A19: 45662 | F19: -55 | I19: =-40-8.08 -> -48.08
A20: 45663 | F20: -30.32 | G20: =-40.2-35.13-29.17 -> -104.5 | H20: =-25.21-12.9-24.23-18 -> -80.34 | K20: =-1385-756 -> -2141
A21: 45664 | G21: -14.99
A22: 45665 | H22: -8.97
A23: 45666 | F23: -15.75
A24: 45667 | E24: -20 | H24: =-1.9*2-2.28-3.02-13.22-27.48 -> -49.8 | L24: -58.32
A25: 45668 | F25: -155 | H25: =-6.39-155.16-16.99-94.49-149 -> -422.03 | I25: =-33.66-15.23 -> -48.89
A26: 45669 | G26: -55
A27: 45670 | H27: -10.55 | K27: -500
A28: 45671 | H28: -49
A29: 45672
A30: 45673 | H30: -69
A31: 45674 | L31: -58.32
A32: 45675 | F32: -140 | G32: -35.54 | H32: =-62.05-86.89-23.47-28.51-3.3 -> -204.22
A33: 45676 | F33: -55 | I33: -47.5
A34: 45677 | F34: -2 | G34: =-40.2-35.13 -> -75.33 | H34: -8.59 | I34: -35 | L34: -19.74
A35: 45678 | G35: -1.24
A36: 45679 | G36: -10.2
A37: 45680 | F37: -129 | H37: =-4.82-0.99-32 -> -37.81
A38: 45681 | F38: =-40+540.11 -> 500.11 | H38: =-72.17-4.41-69.63 -> -146.21 | I38: -38 | L38: -58.32
A39: 45682 | F39: =-40-15-62.2-64.66 -> -181.86 | H39: =-19.9-23.2 -> -43.1
A40: 45683 | I40: =-74.8-55.93 -> -130.73
A41: 45684 | F41: -55 | I41: =-11.38-55.7 -> -67.08
A42: 45685 | G42: =-46-64.99 -> -110.99 | J42: -5000
A43: 45686 | F43: -12 | H43: -2.75 | I43: -4 | L43: -50
A44: 45687 | H44: -178.99 | I44: -83
A45: 45688 | H45: -24.6 | L45: -58.32
A46: 45689 | G46: -9.99 | H46: =-73.38-5.07 -> -78.45
A47: 45690 | F47: -55 | G47: -374.86 | H47: =-1.7-81.82-45.07-22.99 -> -151.58 | K47: -500
A48: 45691 | G48: =-40.2-35.13 -> -75.33 | H48: -40.94 | I48: -51.4
A49: 45692 | G49: -165.71 | H49: -16.4
A50: 45693 | G50: -29.17
A51: 45694 | F51: -26.95 | H51: =-47.34-1.64-35.36-24.72 -> -109.06 | K51: =-sum(756,1385) -> -2141
A52: 45695 | E52: -20 | G52: -14.99 | J52: -318 | L52: -58.32
A53: 45696 | F53: -119 | H53: =-33.16-29.15-16.4 -> -78.71
A54: 45697 | F54: -55 | I54: =-6.5-22.35-12.2 -> -41.05
A55: 45698
A56: 45699 | F56: -97 | H56: -12.45
A57: 45700 | E57: -10 | H57: -43 | I57: -22.5 | J57: 280
A58: 45701 | F58: =-182.66-6.39 -> -189.05 | L58: -50
A59: 45702 | F59: -4 | L59: -58.32
A60: 45703 | H60: =-6-37.56-20.58-83.97 -> -148.11 | I60: -55.81
A61: 45704 | G61: -55
A62: 45705 | F62: =-3.6-25.35 -> -28.95 | G62: =-35.1-40.2-35.13 -> -110.43 | H62: -16.25 | I62: -42
A63: 45706
A64: 45707 | G64: -1.23 | I64: -33.9
A65: 45708 | F65: -15.75 | H65: =-11-47.88-7.09-133.72 -> -199.69
A66: 45709 | H66: =-11.9-30.59 -> -42.49 | I66: -5.4 | L66: -58.32
A67: 45710 | F67: -15.85 | H67: =-11.9-30.59 -> -42.49
A68: 45711 | G68: -55 | H68: =-12.5-4.5 -> -17 | I68: -6.5
A69: 45712 | G69: =-64.99-10.2 -> -75.19 | H69: =-25-6.49-64.7 -> -96.19 | I69: -43.8
A70: 45713 | H70: -14.9
A71: 45714 | I71: -27.41
A72: 45715 | H72: -45.4
A73: 45716 | G73: =-526-46 -> -572 | H73: =-6.1-3.95-34.01-110.98 -> -155.04 | I73: -47.16 | L73: -58.32
A74: 45717 | F74: =-14.99-9.15 -> -24.14 | G74: -9.99
A75: 45718 | G75: -55 | I75: -16.29
A76: 45719 | G76: =-40.2-35.13 -> -75.33
A77: 45720
A78: 45721 | F78: -29.17 | H78: =-40.75-31.28-1.86-12.87 -> -86.76
A79: 45722 | K79: =-1385-756-500 -> -2641
A80: 45723 | G80: -14.99 | I80: -68 | L80: -58.32
A81: 45724 | H81: -23.4
A82: 45725 | F82: -10 | G82: -55 | H82: -7.62
A83: 45726 | H83: =-79.03-2.99-2-0.78 -> -84.8
A84: 45727 | F84: -21.97 | H84: =-4.45-26.24-34.34-24.62 -> -89.65
A85: 45728
A86: 45729 | L86: -5.63
A87: 45730 | H87: -7.5 | I87: -43.85 | L87: -58.32
A88: 45731 | F88: -5 | H88: =-15.16-51.66-53.2 -> -120.02
A89: 45732 | G89: =-12-55 -> -67
A90: 45733 | G90: =-40.2-35.13 -> -75.33
A91: 45734 | G91: -35.07 | H91: =-25.2-52.49-84.03 -> -161.72
A92: 45735 | F92: -12 | G92: -1.23 | I92: -9.5 | L92: -13.14
A93: 45736 | H93: -30.7
A94: 45737 | I94: -45.21 | L94: -58.32
A95: 45738 | F95: 5 | H95: =-3.8-9.66-47.65-54.81-135.07-6.4 -> -257.39
A96: 45739 | F96: 5 | G96: -55 | I96: =-6-4.5-29-4-5 -> -48.5
A97: 45740 | G97: -10.2 | H97: =-77.7-7.37 -> -85.07
A98: 45741 | G98: -64.99 | H98: -1.6 | L98: -50
A99: 45742 | G99: -806.6 | J99: -5000
A100: 45743 | F100: 25.51 | G100: -1720.86 | H100: -75
...

Sheet 2025_income
B1: interest | C1: Will | D1: Yan | E1: Salary Package
B2: =sum(B3:B1000) -> 0 | C2: =sum(C3:C1000) -> 94572.94 | D2: =sum(D3:D1000) -> 11859.25 | E2: =sum(E3:E1000) -> 9507.84
A3: JAN | C3: =3515.61*2 -> 7031.22 | D3: =28.7*2+2122.98 -> 2180.38 | F3: =sum(B3:E3) -> 9211.6
A4: FEB | C4: =3515.61+3647.34 -> 7162.95 | D4: =sum(28.7*2,301.56,487.72) -> 846.68 | F4: =sum(B4:E4) -> 8009.63
A5: MAR | C5: =3515.61*2 -> 7031.22 | D5: =384.17+28.7+101.95+28.7+203.91 -> 747.43 | E5: 768.34 | F5: =sum(B5:E5) -> 8546.99
A6: APR | C6: =3515.61*3 -> 10546.83 | D6: =28.7*2+152.63 -> 210.03 | E6: =sum(454.85,113.71,123.47) -> 692.03 | F6: =sum(B6:E6) -> 11448.89
A7: MAY | C7: =3515.61*2 -> 7031.22 | D7: =28.7*3+101.95*2+210.03 -> 500.03 | E7: =384.17+791.4 -> 1175.57 | F7: =sum(B7:E7) -> 8706.82
A8: JUN | C8: =3641.58*2 -> 7283.16 | D8: =28.7*2+157.22 -> 214.62 | E8: 607.37 | F8: =sum(B8:E8) -> 8105.15
A9: JUL | C9: =3641.5*2 -> 7283 | D9: =157.22+12.3 -> 169.52 | E9: 607.37 | F9: =sum(B9:E9) -> 8059.89
A10: AUG | C10: =3641.58*2 -> 7283.16 | D10: =43.88+4+2826.84+164.24+69.58 -> 3108.54 | E10: 635.45 | F10: =sum(B10:E10) -> 11027.15
A11: SEP | C11: =3641.58*2 -> 7283.16 | D11: =342.67+171.34 -> 514.01 | E11: =1342.35+661.64 -> 2003.99 | F11: =sum(B11:E11) -> 9801.16
A12: OCT | C12: =3641.6*3 -> 10924.8 | D12: =181.41+170.76+171.34 -> 523.51 | E12: =701.95+661.64+661.64 -> 2025.23 | F12: =sum(B12:E12) -> 13473.54
A13: NOV | C13: =3641.58*2 -> 7283.16 | D13: =355.36+1322.59 -> 1677.95 | E13: 992.49 | F13: =sum(B13:E13) -> 9953.6
A14: DEC | C14: =4697.65+3731.41 -> 8429.06 | D14: 1166.55 | F14: =sum(B14:E14) -> 9595.61

Sheet 2024
B1: Expense | C1: Income | D1: Net Profit | E1: Transport | F1: Living | G1: Bill | H1: Groceries | I1: Dine | J1: RMIT | K1: Mortgage | L1: Childcare
B2: =SUM(E2:L2) -> -98959.88 | C2: =SUM(C3:C14) -> 118991.4 | D2: =SUM(B2,C2) -> 20031.52 | E2: =SUM(E15:E1014) -> -4046.87 | F2: =SUM(F15:F1014) -> -17444.05 | G2: =SUM(G15:G1014) -> -13255.01 | H2: =SUM(H15:H1014) -> -14725.16 | I2: =SUM(I16:I1014) -> -5639.63 | J2: =SUM(J15:J1014) -> -7847.74 | K2: =SUM(K15:K1014) -> -32463 | L2: =SUM(L15:L1014) -> -3538.42
A3: 45292 | B3: =SUM(E3:L3) -> -11119.65 | C3: ='2024_income'!F3 -> 10575.24 | D3: =SUM(B3,C3) -> -544.41 | E3: =sum(E15:E45) -> -257.95 | F3: =sum(F15:F45) -> -3513.29 | G3: =sum(G15:G45) -> -724.69 | H3: =sum(H15:H45) -> -1693.19 | I3: =sum(I16:I45) -> -505.66 | J3: =sum(J15:J45) -> -1300 | K3: =sum(K15:K45) -> -2629 | L3: =sum(L15:L45) -> -495.87
A4: 45323 | B4: =SUM(E4:L4) -> -7312.46 | C4: ='2024_income'!F4 -> 7525.17 | D4: =SUM(B4,C4) -> 212.71 | E4: =SUM(E46:E73) -> -100 | F4: =SUM(F46:F73) -> -322.16 | G4: =SUM(G46:G73) -> -953.36 | H4: =SUM(H46:H73) -> -1430.25 | I4: =SUM(I46:I73) -> -272.75 | J4: =SUM(J46:J73) -> -1451.74 | K4: =SUM(K46:K73) -> -2529 | L4: =SUM(L46:L73) -> -253.2
A5: 45352 | B5: =SUM(E5:L5) -> -9126.06 | C5: ='2024_income'!F5 -> 8490.39 | D5: =SUM(B5,C5) -> -635.67 | E5: =sum(E74:E104) -> -2423.12 | F5: =sum(F74:F104) -> -1021.26 | G5: =sum(G74:G104) -> -878.26 | H5: =sum(H74:H104) -> -910.89 | I5: =sum(I74:I104) -> -717.93 | J5: =sum(J74:J104) -> -196 | K5: =sum(K74:K104) -> -2641 | L5: =sum(L74:L104) -> -337.6
A6: 45383 | B6: =SUM(E6:L6) -> -6446.79 | C6: ='2024_income'!F6 -> 8352.56 | D6: =SUM(B6,C6) -> 1905.77 | E6: =sum(E105:E134) -> -65.13 | F6: =sum(F105:F134) -> -823.7 | G6: =sum(G105:G134) -> -1059.95 | H6: =sum(H105:H134) -> -1094.51 | I6: =sum(I105:I134) -> -424.9 | J6: =sum(J105:J134) -> 0 | K6: =sum(K105:K134) -> -2641 | L6: =sum(L105:L134) -> -337.6
A7: 45413 | B7: =SUM(E7:L7) -> -7983.29 | C7: ='2024_income'!F7 -> 12660.31 | D7: =SUM(B7,C7) -> 4677.02 | E7: =sum(E135:E165) -> -31.78 | F7: =sum(F135:F165) -> -2097.2 | G7: =sum(G135:G165) -> -879.95 | H7: =sum(H135:H165) -> -1215.77 | I7: =sum(I135:I165) -> -491.3 | J7: =sum(J135:J165) -> 0 | K7: =sum(K135:K165) -> -2641 | L7: =sum(L135:L165) -> -626.29
A8: 45444 | B8: =SUM(E8:L8) -> -5040.56 | C8: ='2024_income'!F8 -> 8567.76 | D8: =SUM(B8,C8) -> 3527.2 | E8: =sum(E166:E195) -> -22.69 | F8: =sum(F166:F195) -> -634.96 | G8: =sum(G166:G195) -> -507.21 | H8: =sum(H166:H195) -> -815.94 | I8: =sum(I166:I195) -> -551.96 | J8: =sum(J166:J195) -> 0 | K8: =sum(K166:K195) -> -2641 | L8: =sum(L166:L195) -> 133.2
A9: 45474 | B9: =SUM(E9:L9) -> -10938 | C9: ='2024_income'!F9 -> 9068.08 | D9: =SUM(B9,C9) -> -1869.92 | E9: =sum(E196:E226) -> -27.3 | F9: =sum(F196:F226) -> -2619.91 | G9: =sum(G196:G226) -> -3237.06 | H9: =sum(H196:H226) -> -1474.93 | I9: =sum(I196:I226) -> -261.57 | J9: =sum(J196:J226) -> 0 | K9: =sum(K196:K226) -> -3036 | L9: =sum(L196:L226) -> -281.23
A10: 45505 | B10: =SUM(E10:L10) -> -5781.3 | C10: ='2024_income'!F10 -> 9605.22 | D10: =SUM(B10,C10) -> 3823.92 | E10: =sum(E227:E257) -> -22 | F10: =sum(F227:F257) -> -529.98 | G10: =sum(G227:G257) -> -635.39 | H10: =sum(H227:H257) -> -1098.01 | I10: =sum(I227:I257) -> -563.32 | J10: =sum(J227:J257) -> 0 | K10: =sum(K227:K257) -> -2641 | L10: =sum(L227:L257) -> -291.6
A11: 45536 | B11: =SUM(E11:L11) -> -6120.54 | C11: ='2024_income'!F11 -> 9605.22 | D11: =SUM(B11,C11) -> 3484.68 | E11: =SUM(E258:E287) -> -20 | F11: =SUM(F258:F287) -> -482.07 | G11: =SUM(G258:G287) -> -1204.66 | H11: =SUM(H258:H287) -> -1141.4 | I11: =SUM(I258:I287) -> -498.13 | J11: =SUM(J258:J287) -> 100 | K11: =SUM(K258:K287) -> -2641 | L11: =SUM(L258:L287) -> -233.28
A12: 45566 | B12: =SUM(E12:L12) -> -6570.89 | C12: ='2024_income'!F12 -> 14627.4 | D12: =SUM(B12,C12) -> 8056.51 | E12: =SUM(E288:E318) -> 0 | F12: =SUM(F288:F318) -> -1809.57 | G12: =SUM(G288:G318) -> -869.32 | H12: =SUM(H288:H318) -> -961.93 | I12: =SUM(I288:I318) -> -84.95 | J12: =SUM(J288:J318) -> 0 | K12: =SUM(K288:K318) -> -2641 | L12: =SUM(L288:L318) -> -204.12
A13: 45597 | B13: =SUM(E13:L13) -> -8771.89 | C13: ='2024_income'!F13 -> 9694.22 | D13: =SUM(B13,C13) -> 922.33 | E13: =SUM(E319:E348) -> -976.9 | F13: =SUM(F319:F348) -> -2463.72 | G13: =SUM(G319:G348) -> -666.35 | H13: =SUM(H319:H348) -> -1549.13 | I13: =SUM(I319:I348) -> -630.21 | J13: =SUM(J319:J348) -> 0 | K13: =SUM(K319:K348) -> -2141 | L13: =SUM(L319:L348) -> -344.58
A14: 45627 | B14: =SUM(E14:L14) -> -13748.45 | C14: ='2024_income'!F14 -> 10219.83 | D14: =SUM(B14,C14) -> -3528.62 | E14: =SUM(E349:E379) -> -100 | F14: =SUM(F349:F379) -> -1126.23 | G14: =SUM(G349:G379) -> -1638.81 | H14: =SUM(H349:H379) -> -1339.21 | I14: =SUM(I349:I379) -> -636.95 | J14: =SUM(J349:J379) -> -5000 | K14: =SUM(K349:K379) -> -3641 | L14: =SUM(L349:L379) -> -266.25
A15: 45292 | G15: -9.99
A16: 45293
A17: 45294 | F17: -272 | H17: =-sum(65.75,25) -> -90.75 | I17: =-sum(5,71.05) -> -76.05 | J17: -1300
A18: 45295 | F18: =-sum(5.5,105) -> -110.5 | G18: -48.3 | H18: =-sum(13.36,20.3) -> -33.66 | I18: -9.5
A19: 45296 | E19: -50 | G19: =-Sum(29.17,20.3) -> -49.47 | H19: =-sum(6,8.97) -> -14.97 | L19: -116.07
A20: 45297 | H20: -235.98
A21: 45298 | F21: =-Sum(13.95,12.97,0.5,24.98,19) -> -71.4 | H21: =-sum(18.65,3.14,9.9) -> -31.69 | I21: -39.69
A22: 45299 | E22: -33.84 | F22: =-Sum(14.8,5,3) -> -22.8 | H22: -11.22 | K22: =-sum(1385,744) -> -2129
A23: 45300 | E23: -13.5 | F23: -111.3 | H23: -1.25
A24: 45301 | F24: -4 | H24: =-sum(18.75,20.4) -> -39.15 | I24: -9.8
A25: 45302 | F25: -15.25 | H25: =-sum(48.94,85) -> -133.94 | K25: -500
A26: 45303 | H26: =-sum(26.9,13.62) -> -40.52 | I26: -36.54 | L26: -126.6
A27: 45304 | E27: -51.27 | F27: 4 | G27: -4.49 | H27: -20.15 | I27: -79.86
A28: 45305 | F28: =-69.96*2 -> -139.92 | H28: =-sum(28,-10,12,11) -> -41 | I28: -61.71
A29: 45306 | H29: =-sum(4.4,28.56) -> -32.96
A30: 45307 | E30: -10 | F30: -31 | H30: =-sum(11,20.1,16,7.5,68.2) -> -122.8 | I30: =-sum(9.5,13.7,12.58) -> -35.78
A31: 45308 | E31: -20 | F31: -18.8 | G31: -33.43 | H31: =-sum(54.5) -> -54.5
A32: 45309 | E32: -10 | F32: -1 | G32: -48.3 | H32: =-sum(23.14,9.88,14.42) -> -47.44 | I32: -4.6 | L32: -126.6
A33: 45310 | E33: =-sum(8,50) -> -58 | F33: -9 | I33: =-sum(8.4,26) -> -34.4
A34: 45311 | F34: -12.02 | H34: =-Sum(38.8,40.88,4.2,7.57,23.65,17.42) -> -132.52 | I34: -60.9
A35: 45312
A36: 45313 | E36: -11.34 | F36: =-Sum(9.55,18) -> -27.55 | G36: -33.84
A37: 45314 | F37: =-sum(18,80,20.99) -> -118.99 | G37: -98.4 | H37: =-sum(18.01,16,5.26) -> -39.27
A38: 45315 | F38: -2.29 | H38: =-sum(210,11.21,37.35) -> -258.56
A39: 45316 | F39: =-sum(3,20,4.8) -> -27.8 | H39: =-sum(12,22.05,18,7.95) -> -60
A40: 45317 | F40: -157.8 | H40: =-sum(28.96,7.62) -> -36.58 | I40: -7.27
A41: 45318 | F41: -38.42 | I41: =-sum(34.56,15) -> -49.56
A42: 45319 | F42: -200 | H42: =-sum(26.16,70.11) -> -96.27
A43: 45320 | F43: -2078 | G43: -64.99 | H43: =-sum(6.1,21.99) -> -28.09 | L43: -126.6
A44: 45321 | F44: =-sum(39.95,7.5) -> -47.45 | G44: -333.48 | H44: =-sum(56) -> -56
A45: 45322 | H45: =-sum(14.47,3.06,16.39) -> -33.92
A46: 45323 | F46: =-sum(14.8,141) -> -155.8 | G46: =-sum(9.99,48.3) -> -58.29 | H46: =-Sum(16.16,14.35) -> -30.51
A47: 45324 | E47: -50 | F47: -30 | H47: =-sum(5.23,21.7) -> -26.93 | J47: -500 | L47: -84.4
A48: 45325 | E48: -50 | F48: -14.17 | H48: =-sum(12,15.1,10,12) -> -49.1 | J48: -500
A49: 45326 | I49: -27.5
A50: 45327 | G50: =-sum(33.84,38.21,29.17) -> -101.22 | H50: =-sum(6.43,22.47) -> -28.9
A51: 45328 | F51: -9.45 | H51: -11.7 | K51: =-sum(1385,744) -> -2129
A52: 45329 | F52: -10 | G52: -126.96 | H52: =-sum(27.99,16.26,65.58) -> -109.83
A53: 45330 | F53: -4.49
A54: 45331 | F54: =-Sum(4,34) -> -38 | H54: -47.88 | I54: -57.8
A55: 45332 | H55: =-Sum(31.65,46) -> -77.65
A56: 45333 | H56: =-sum(9.5,17.55,2) -> -29.05 | I56: -36.1
A57: 45334 | H57: -10.85
A58: 45335 | G58: -4.49 | H58: =-sum(6,24.44,139.2,-10) -> -159.64 | J58: -300
A59: 45336 | H59: -24.4 | K59: -400
A60: 45337 | G60: -48.3 | H60: =-sum(19.09,10,12.2,8.09,27.26,6.13) -> -82.77
A61: 45338 | G61: -33.87 | H61: =-sum(17.99,49.7,12,10.9,7.15) -> -97.74 | I61: =-sum(53.8,43) -> -96.8 | L61: -84.4
A62: 45339 | H62: -6.6
A63: 45340 | H63: -21.05
A64: 45341 | G64: =-sum(33.84,1.02) -> -34.86 | H64: =-sum(5.29,6.12) -> -11.41
A65: 45342 | H65: =-sum(22.14,14.65) -> -36.79
A66: 45343 | G66: -20.22 | H66: =-sum(2,9.9,10.06,11.55,8.98,7.57) -> -50.06
A67: 45344 | F67: =-sum(15,15.25) -> -30.25 | G67: -4.16 | H67: =-sum(4.6,11.99,12,8.42,12.72) -> -49.73
A68: 45345 | G68: -64.99 | H68: =-sum(-20,15.02,60.99,16,4.4,10.05) -> -86.46 | I68: =-sum(4.95,14.08) -> -19.03 | L68: -84.4
A69: 45346 | H69: -210.7
A70: 45347 | H70: =-sum(19.2,25.15) -> -44.35
A71: 45348 | F71: =-sum(5,15) -> -20 | H71: =-sum(23.97,15.52,19.03) -> -58.52
A72: 45349 | F72: -10 | H72: =-sum(18.99,11.2) -> -30.19
A73: 45350 | G73: -456 | H73: =-sum(16.4,2.99,18.05) -> -37.44 | I73: -35.52 | J73: -151.74
A74: 45352 | G74: =-Sum(48.3,9.9) -> -58.2 | L74: -84.4
A75: 45353 | H75: -11.35
A76: 45354 | F76: -15 | I76: -66.12 | J76: -200
A77: 45355 | G77: -33.84 | H77: =-sum(3.1,3.29,35.15) -> -41.54 | I77: -71.12
A78: 45356 | F78: =-sum(28.75,449,-200) -> -277.75 | G78: -97
A79: 45357 | F79: -160 | G79: -29.17 | H79: -53.35 | I79: -42.36 | K79: =-sum(1385,756) -> -2141
A80: 45358 | F80: -30.82 | G80: -39.1 | H80: =-sum(51,34.3) -> -85.3 | I80: =-Sum(19.1,54.81,4.6) -> -78.51
A81: 45359 | F81: -47.2 | I81: -16.5 | J81: 4 | L81: -84.4
A82: 45360 | I82: -51
A83: 45361 | H83: -14 | I83: =-sum(6.09,44.25) -> -50.34
A84: 45362 | H84: =-sum(76.07,1.78) -> -77.85 | I84: -5.76
A85: 45363
A86: 45364 | G86: -4.49 | H86: -11.1
A87: 45365 | G87: -48.3 | H87: =-sum(3.95,23.52,5.88) -> -33.35 | I87: -11.67
A88: 45366 | F88: -29.95 | H88: =-sum(26.9,3.55,10.06) -> -40.51 | I88: -6.6 | L88: -84.4
A89: 45367 | I89: -6.05
A90: 45368 | F90: =-sum(14.9,10) -> -24.9 | G90: -33.59 | H90: -28.9 | I90: =-sum(13.7,48.5) -> -62.2
A91: 45369 | G91: =-sum(240,33.8) -> -273.8 | H91: =-sum(8,17.68) -> -25.68 | I91: =-sum(4.24,10.2) -> -14.44
A92: 45370 | G92: -1.01 | H92: =-sum(2,5.24) -> -7.24 | I92: -13.7
A93: 45371 | F93: -19.3 | G93: -115.57 | H93: -29.2 | I93: -66.48
A94: 45372 | E94: -776.29 | F94: -6.99 | H94: =-sum(6.94,49.38,13.29) -> -69.61 | K94: -500
A95: 45373 | E95: -50 | H95: -33.48
A96: 45374 | F96: -101.97 | H96: =-sum(11.9,46.2) -> -58.1 | I96: -50.5
A97: 45375 | F97: =-sum(97.92,6,3,5) -> -111.92 | I97: =-sum(3) -> -3
A98: 45376 | F98: -111.7 | G98: -10.2 | I98: =-sum(21.4,13.9) -> -35.3 | L98: -84.4
A99: 45377 | E99: -1576.83 | G99: -64.99 | H99: =-sum(3.77,26.61,6.55,9.77) -> -46.7
A100: 45378 | E100: -20 | H100: =-sum(22.2,97.72,32.85) -> -152.77
...

Sheet 2024_income
B1: interest | C1: Will | D1: Yan | E1: Salary Package
B2: =sum(B3:B1000) -> 412.55 | C2: =sum(C3:C1000) -> 83017.75 | D2: =sum(D3:D1000) -> 28504.1 | E2: =sum(E3:E1000) -> 7057
A3: JAN | B3: =sum(133.02,1.24) -> 134.26 | C3: =sum(200,3043.41*2) -> 6286.82 | D3: =sum(2534.19,648.33) -> 3182.52 | E3: =sum(375.41*2,110.41*2) -> 971.64 | F3: =sum(B3:E3) -> 10575.24
A4: FEB | B4: =sum(141.7,1.32) -> 143.02 | C4: =sum(568.94,1501.5,3043.41) -> 5113.85 | D4: =648.33*2 -> 1296.66 | E4: =sum(375.41*2,110.41*2) -> 971.64 | F4: =sum(B4:E4) -> 7525.17
A5: MAR | B5: 135.27 | C5: =3043.41*2 -> 6086.82 | D5: =sum(648.33*2) -> 1296.66 | E5: =sum(375.41*2,110.41*2) -> 971.64 | F5: =sum(B5:E5) -> 8490.39
A6: APR | C6: =3043.41*2 -> 6086.82 | D6: =sum(684.42*2) -> 1368.84 | E6: =sum(346.53*2,101.92*2) -> 896.9 | F6: =sum(B6:E6) -> 8352.56
A7: MAY | C7: =3043.41*3 -> 9130.23 | D7: =sum(684.42*2,815.89) -> 2184.73 | E7: =sum(346.53*3,101.92*3) -> 1345.35 | F7: =sum(B7:E7) -> 12660.31
A8: JUN | C8: =3151.01*2 -> 6302.02 | D8: =sum(684.42*2) -> 1368.84 | E8: =sum(346.53*2,101.92*2) -> 896.9 | F8: =sum(B8:E8) -> 8567.76
A9: JUL | C9: =3245.01*2 -> 6490.02 | D9: =sum(684.42*2,312.32) -> 1681.16 | E9: =sum(346.53*2,101.92*2) -> 896.9 | F9: =sum(B9:E9) -> 9068.08
A10: AUG | C10: =3245.01*2 -> 6490.02 | D10: =sum(1557.6*2) -> 3115.2 | F10: =sum(B10:E10) -> 9605.22
A11: SEP | C11: =3245.01*2 -> 6490.02 | D11: =1557.6*2 -> 3115.2 | F11: =sum(B11:E11) -> 9605.22
A12: OCT | C12: =3291.24+3302.3+3361.06 -> 9954.6 | D12: =1557.6*3 -> 4672.8 | F12: =sum(B12:E12) -> 14627.4
A13: NOV | C13: =3331.68*2 -> 6663.36 | D13: =sum(100.45,8.2,1557.6,12.3,1246.28) -> 2924.83 | E13: 106.03 | F13: =sum(B13:E13) -> 9694.22
A14: DEC | C14: =4407.56+3515.61 -> 7923.17 | D14: =28.7+2239.26+28.7 -> 2296.66 | F14: =sum(B14:E14) -> 10219.83

Sheet 2023
B1: Expense | C1: Income | D1: Net Profit | E1: Transport | F1: Living | G1: Bill | H1: Groceries | I1: Dine | J1: RMIT | K1: Mortgage | L1: Childcare
B2: =SUM(E2:L2) -> -123129.62 | C2: =SUM(C3:C14) -> 144448.9 | D2: =SUM(B2,C2) -> 21319.28 | E2: =SUM(E15:E1014) -> -8027.07 | F2: =SUM(F15:F1014) -> -14490.58 | G2: =SUM(G15:G1014) -> -16218.56 | H2: =SUM(H15:H1014) -> -16387.07 | I2: =SUM(I16:I1014) -> -6975.84 | J2: =SUM(J15:J1014) -> -20704.7 | K2: =SUM(K15:K1014) -> -32070 | L2: =SUM(L15:L1014) -> -8255.8
A3: 44927 | B3: =SUM(E3:L3) -> -5886.78 | C3: ='2023_income'!F3 -> 12655.27 | D3: =SUM(B3,C3) -> 6768.49 | E3: =sum(E15:E45) -> -20 | F3: =sum(F15:F45) -> -295.51 | G3: =sum(G15:G45) -> -612.07 | H3: =sum(H15:H45) -> -1289.48 | I3: =sum(I16:I45) -> -665.32 | J3: =sum(J15:J45) -> 0 | K3: =sum(K15:K45) -> -2540 | L3: =sum(L15:L45) -> -464.4
A4: 44958 | B4: =SUM(E4:L4) -> -7471.21 | C4: ='2023_income'!F4 -> 8569.45 | D4: =SUM(B4,C4) -> 1098.24 | E4: =SUM(E46:E73) -> 0 | F4: =SUM(F46:F73) -> -677.03 | G4: =SUM(G46:G73) -> -1338.47 | H4: =SUM(H46:H73) -> -1768.98 | I4: =SUM(I46:I73) -> -433.3 | J4: =SUM(J46:J73) -> 0 | K4: =SUM(K46:K73) -> -2540 | L4: =SUM(L46:L73) -> -713.43
A5: 44986 | B5: =SUM(E5:L5) -> -10331.23 | C5: ='2023_income'!F5 -> 11967.09 | D5: =SUM(B5,C5) -> 1635.86 | E5: =sum(E74:E104) -> -1914.72 | F5: =sum(F74:F104) -> -345.12 | G5: =sum(G74:G104) -> -3050.02 | H5: =sum(H74:H104) -> -1059.23 | I5: =sum(I74:I104) -> -512.64 | J5: =sum(J74:J104) -> 0 | K5: =sum(K74:K104) -> -2590 | L5: =sum(L74:L104) -> -859.5
A6: 45017 | B6: =SUM(E6:L6) -> -6071.86 | C6: ='2023_income'!F6 -> 14947.84 | D6: =SUM(B6,C6) -> 8875.98 | E6: =sum(E105:E134) -> -13.44 | F6: =sum(F105:F134) -> -169.06 | G6: =sum(G105:G134) -> -585.07 | H6: =sum(H105:H134) -> -1250.69 | I6: =sum(I105:I134) -> -833.3 | J6: =sum(J105:J134) -> 0 | K6: =sum(K105:K134) -> -2590 | L6: =sum(L105:L134) -> -630.3
A7: 45047 | B7: =SUM(E7:L7) -> -7050.33 | C7: ='2023_income'!F7 -> 14634.99 | D7: =SUM(B7,C7) -> 7584.66 | E7: =sum(E135:E165) -> -204.15 | F7: =sum(F135:F165) -> -230.58 | G7: =sum(G135:G165) -> -1468.64 | H7: =sum(H135:H165) -> -1311.57 | I7: =sum(I135:I165) -> -527.79 | J7: =sum(J135:J165) -> -30 | K7: =sum(K135:K165) -> -2590 | L7: =sum(L135:L165) -> -687.6
A8: 45078 | B8: =SUM(E8:L8) -> -8517.79 | C8: ='2023_income'!F8 -> 11352.46 | D8: =SUM(B8,C8) -> 2834.67 | E8: =sum(E166:E195) -> -41.5 | F8: =sum(F166:F195) -> -535.16 | G8: =sum(G166:G195) -> -1739.75 | H8: =sum(H166:H195) -> -1384.54 | I8: =sum(I166:I195) -> -675.75 | J8: =sum(J166:J195) -> -430 | K8: =sum(K166:K195) -> -2590 | L8: =sum(L166:L195) -> -1121.09
A9: 45108 | B9: =SUM(E9:L9) -> -13309.72 | C9: ='2023_income'!F9 -> 10376.98 | D9: =SUM(B9,C9) -> -2932.74 | E9: =sum(E196:E226) -> -80 | F9: =sum(F196:F226) -> -5493.31 | G9: =sum(G196:G226) -> -2661.45 | H9: =sum(H196:H226) -> -1030.41 | I9: =sum(I196:I226) -> -386.81 | J9: =sum(J196:J226) -> -214.15 | K9: =sum(K196:K226) -> -2985 | L9: =sum(L196:L226) -> -458.59
A10: 45139 | B10: =SUM(E10:L10) -> -7082.04 | C10: ='2023_income'!F10 -> 10836.53 | D10: =SUM(B10,C10) -> 3754.49 | E10: =sum(E227:E257) -> -4359.75 | F10: =sum(F227:F257) -> 4327.71 | G10: =sum(G227:G257) -> -961.65 | H10: =sum(H227:H257) -> -1307.77 | I10: =sum(I227:I257) -> -654.53 | J10: =sum(J227:J257) -> -30.55 | K10: =sum(K227:K257) -> -2629 | L10: =sum(L227:L257) -> -1466.5
A11: 45170 | B11: =SUM(E11:L11) -> -7514.69 | C11: ='2023_income'!F11 -> 10501.82 | D11: =SUM(B11,C11) -> 2987.13 | E11: =SUM(E258:E287) -> -24 | F11: =SUM(F258:F287) -> -1683.58 | G11: =SUM(G258:G287) -> -466.3 | H11: =SUM(H258:H287) -> -1489.12 | I11: =SUM(I258:I287) -> -607.4 | J11: =SUM(J258:J287) -> 0 | K11: =SUM(K258:K287) -> -2629 | L11: =SUM(L258:L287) -> -615.29
A12: 45200 | B12: =SUM(E12:L12) -> -8817.13 | C12: ='2023_income'!F12 -> 11032.25 | D12: =SUM(B12,C12) -> 2215.12 | E12: =SUM(E288:E318) -> -20 | F12: =SUM(F288:F318) -> -2181.3 | G12: =SUM(G288:G318) -> -1485.91 | H12: =SUM(H288:H318) -> -1517.11 | I12: =SUM(I288:I318) -> -733.85 | J12: =SUM(J288:J318) -> 0 | K12: =SUM(K288:K318) -> -2629 | L12: =SUM(L288:L318) -> -249.96
A13: 45231 | B13: =SUM(E13:L13) -> -11427.02 | C13: ='2023_income'!F13 -> 17470.73 | D13: =SUM(B13,C13) -> 6043.71 | E13: =SUM(E319:E348) -> -1126.33 | F13: =SUM(F319:F348) -> -3385.59 | G13: =SUM(G319:G348) -> -1283.8 | H13: =SUM(H319:H348) -> -1926.97 | I13: =SUM(I319:I348) -> -565.93 | J13: =SUM(J319:J348) -> 0 | K13: =SUM(K319:K348) -> -2629 | L13: =SUM(L319:L348) -> -509.4
A14: 45261 | B14: =SUM(E14:L14) -> -29649.82 | C14: ='2023_income'!F14 -> 10103.49 | D14: =SUM(B14,C14) -> -19546.33 | E14: =SUM(E349:E379) -> -223.18 | F14: =SUM(F349:F379) -> -3822.05 | G14: =SUM(G349:G379) -> -565.43 | H14: =SUM(H349:H379) -> -1051.2 | I14: =SUM(I349:I379) -> -379.22 | J14: =SUM(J349:J379) -> -20000 | K14: =SUM(K349:K379) -> -3129 | L14: =SUM(L349:L379) -> -479.74
A15: 44927 | G15: -9.99
A16: 44928 | F16: -5.25 | H16: =-sum(16.99,2.9) -> -19.89 | I16: =-sum(70.15,22) -> -92.15
A17: 44929 | F17: -24.69 | G17: -23.3 | I17: =-sum(18,16,4.9) -> -38.9
A18: 44930 | H18: -31.05
A19: 44931 | H19: -22
A20: 44932 | G20: -29.17 | K20: =-sum(655,1385) -> -2040 | L20: -116.6
A21: 44933 | H21: =-sum(53.07,48.73,38.51) -> -140.31 | I21: -44
A22: 44934 | K22: -500
A23: 44935 | G23: -23.3
A24: 44936 | H24: =-sum(135.13,61.09) -> -196.22
A25: 44937 | F25: -15 | I25: 6.09
A26: 44938
A27: 44939 | F27: -15 | H27: =-sum(7.2,5.5,16.29) -> -28.99 | L27: -116.6
A28: 44940 | F28: =-sum(67.47,6) -> -73.47 | H28: =-sum(17.35,32.94) -> -50.29
A29: 44941 | H29: =-sum(63.85,39.92) -> -103.77 | I29: -37.5
A30: 44942 | G30: =-sum(23.3*2) -> -46.6
A31: 44943
A32: 44944 | H32: =-sum(30.95) -> -30.95 | I32: =-sum(8.5,16) -> -24.5
A33: 44945
A34: 44946 | H34: =-sum(-12.5,-9,56.08,45.15,24.41) -> -104.14 | I34: -8.4 | L34: -116.6
A35: 44947 | G35: =-sum(33.5,40.03,23.3) -> -96.83 | H35: =-sum(23.09,30.98,1.2,35,17.55,-9,68) -> -166.82
A36: 44948 | F36: -60.6 | H36: =-sum(26,12.5,5.6,17.5) -> -61.6 | I36: -96.14
A37: 44949 | F37: -50 | G37: -23.3
A38: 44950 | E38: -20 | I38: =-sum(7.5,89.83) -> -97.33
A39: 44951 | G39: -64.99
A40: 44952 | F40: -25 | G40: -247.99 | H40: -15.3 | I40: -35.11
A41: 44953 | L41: -114.6
A42: 44954 | H42: =-sum(14.15,59.41,80.82) -> -154.38 | I42: -8.7
A43: 44955 | I43: -93.5
A44: 44956 | G44: =-23.3*2 -> -46.6 | H44: =-sum(67.45,8.5) -> -75.95 | I44: -42.22
A45: 44957 | F45: -26.5 | H45: -87.82 | I45: =-SUM(10.74,42.22) -> -52.96
A46: 44958 | G46: -9.99
A47: 44959 | H47: -25.15
A48: 44960 | H48: =-sum(15,13.36,60) -> -88.36 | K48: -500 | L48: -171.9
A49: 44961 | H49: =-sum(28.6,33.3,28.64) -> -90.54 | I49: -8.4
A50: 44962 | G50: -29.17 | H50: =-sum(22.09,103.38,3.3) -> -128.77 | I50: -58.8
A51: 44963 | G51: =-sum(23.3,23.3,33.5) -> -80.1 | H51: -12 | K51: =-sum(655,1385) -> -2040
A52: 44964 | F52: -49.48 | H52: -25.83 | L52: -25.83
A53: 44965 | I53: -21.8
A54: 44966 | F54: -105.4 | G54: -57.19 | I54: =-sum(13.5,6) -> -19.5
A55: 44967 | L55: -171.9
A56: 44968 | F56: -109 | H56: -266
A57: 44969 | F57: =-sum(11.98,2.99) -> -14.97 | H57: =-sum(40,13,265.37,71.15,4.01) -> -393.53 | I57: -22.7
A58: 44970 | G58: -23.3
A59: 44971 | G59: -23.3 | H59: -27.8 | I59: -26.85
A60: 44972 | G60: -490 | H60: -9.47 | I60: -32.43 | L60: -171.9
A61: 44973
A62: 44974 | F62: -30
A63: 44975 | H63: =-sum(42.73,4.2,29.94,14.8) -> -91.67 | I63: -8.7
A64: 44976 | H64: =-sum(51.01,39.98,17.99) -> -108.98 | I64: =-sum(4.48,49.25,6.5) -> -60.23
A65: 44977 | F65: 14.37 | G65: =-sum(33.5,23.3) -> -56.8
A66: 44978 | F66: 14.05 | H66: =-Sum(15,49.1,7.41,55,44.68) -> -171.19 | I66: -36.5
A67: 44979 | F67: -15 | G67: -40.03 | H67: =-sum(7.75,14.9) -> -22.65
A68: 44980 | G68: -64.99
A69: 44981 | F69: -210 | L69: -171.9
A70: 44982 | H70: =-sum(84.94,17.1) -> -102.04 | I70: -50.44
A71: 44983 | H71: -6.2 | I71: -18.2
A72: 44984 | F72: =-sum(200,-44.4) -> -155.6 | G72: =-23.3*2 -> -46.6 | H72: =-sum(6,6.3,3.03,11.15) -> -26.48 | I72: -32.8
A73: 44985 | F73: =-sum(16) -> -16 | G73: -417 | H73: =-sum(81.11,-7,11.75,33.16,53.3) -> -172.32 | I73: -35.95
A74: 44986 | G74: -9.99
A75: 44987 | F75: 44.4 | H75: -11.45 | I75: -50.5
A76: 44988 | L76: -171.9
A77: 44989 | H77: =-sum(2.95,46.99) -> -49.94 | I77: -32
A78: 44990 | H78: =-sum(26.74,8.2,16.5,9.45) -> -60.89
A79: 44991 | G79: =-sum(33.5,23.3*2,29.17) -> -109.27 | K79: =-sum(705,1385) -> -2090
A80: 44992
A81: 44993 | H81: -21.25 | I81: -6
A82: 44994
A83: 44995 | L83: -171.9
A84: 44996 | H84: =-sum(64.36,21.13,14.8,2.8,58.7) -> -161.79
A85: 44997 | H85: =-sum(3.5,6.75,13.1) -> -23.35 | I85: -15
A86: 44998 | F86: -100.78 | G86: =-23.3*2 -> -46.6 | K86: -500
A87: 44999 | F87: -19.92 | H87: -19.1 | I87: =-sum(10.15,86.1,15) -> -111.25
A88: 45000
A89: 45001
A90: 45002 | G90: =-sum(764.7,1796.85) -> -2561.55 | H90: =-sum(38,13) -> -51 | I90: -42.4 | L90: -171.9
A91: 45003 | G91: -34.39
A92: 45004 | H92: =-sum(15,19,5,15,92.51,7) -> -153.51 | I92: -60.75
A93: 45005 | G93: =-sum(23.3*2,33.5) -> -80.1
A94: 45006 | E94: -20 | F94: =-sum(3,24.49) -> -27.49 | G94: -19.07 | H94: =-sum(58.32,26.88) -> -85.2
A95: 45007 | G95: -40.03 | H95: =-sum(3) -> -3
A96: 45008 | E96: =-sum(1815.07,79.65) -> -1894.72 | F96: -97.61 | H96: =-sum(6.88,39.98) -> -46.86
A97: 45009 | F97: -73.75 | L97: -171.9
A98: 45010 | H98: =-sum(15,58.35,57.6,47,29.99) -> -207.94 | I98: -71.34
A99: 45011
A100: 45012 | G100: -46.6 | H100: =-sum(59.97) -> -59.97 | I100: -56.8
...

Sheet 2023_income
B1: interest | C1: Will | D1: Yan | E1: Salary Package
B2: =sum(B3:B1000) -> 620.32 | C2: =sum(C3:C1000) -> 170565.1 | D2: =sum(D3:D1000) -> 51723.57 | E2: =sum(E3:E1000) -> 18954.23
A3: JAN | C3: =2677.26*2 -> 5354.52 | D3: =sum(1886.39,2125.84,1798.63) -> 5810.86 | E3: =sum(342.06*3,154.57*3) -> 1489.89 | F3: =sum(B3:E3) -> 12655.27
A4: Feb | C4: =2677.26*2 -> 5354.52 | D4: =sum(2718.3) -> 2718.3 | E4: =sum(342.06,154.57) -> 496.63 | F4: =sum(B4:E4) -> 8569.45
A5: MAR | C5: =2677.26*2 -> 5354.52 | D5: =sum(1624.89,1806.27,1846.09) -> 5277.25 | E5: =sum(342.06*3,154.57*2) -> 1335.32 | F5: =sum(B5:E5) -> 11967.09
A6: APR | B6: 0.5 | C6: =sum(2718.98,2722.06) -> 5441.04 | D6: =sum(73.6,2590.06) -> 2663.66 | E6: =sum(3900,2942.64) -> 6842.64 | F6: =sum(B6:E6) -> 14947.84
A7: MAY | B7: 23.63 | C7: =2722.06*3 -> 8166.18 | D7: =sum(1771.51,1916,1741.04) -> 5428.55 | E7: =sum(375.41*2,155.41,110.4) -> 1016.63 | F7: =sum(B7:E7) -> 14634.99
A8: JUN | B8: =sum(49.69,0.48) -> 50.17 | C8: =2794.07*2 -> 5588.14 | D8: =sum(2113.91,2142.78) -> 4256.69 | E8: =sum(110.41*3,375.41*3) -> 1457.46 | F8: =sum(B8:E8) -> 11352.46
A9: JUL | B9: =sum(61.09,0.57) -> 61.66 | C9: =2794.07*2 -> 5588.14 | D9: =sum(1888.3,1867.24) -> 3755.54 | E9: =sum(375.41*2,110.41*2) -> 971.64 | F9: =sum(B9:E9) -> 10376.98
A10: AUG | B10: =sum(70.12,0.64) -> 70.76 | C10: =2794.07*2 -> 5588.14 | D10: =sum(2211.12,1994.87) -> 4205.99 | E10: =sum(375.41*2,110.41*2) -> 971.64 | F10: =sum(B10:E10) -> 10836.53
A11: SEP | B11: 79.92 | C11: =2794.07*2 -> 5588.14 | D11: =sum(2266.96,1595.16) -> 3862.12 | E11: =sum(375.41*2,110.41*2) -> 971.64 | F11: =sum(B11:E11) -> 10501.82
A12: OCT | B12: 93.59 | C12: =3043.41*2 -> 6086.82 | D12: =sum(2116.97,1763.23) -> 3880.2 | E12: =sum(375.41*2,110.41*2) -> 971.64 | F12: =sum(B12:E12) -> 11032.25
A13: NOV | B13: 115.98 | C13: =3041.43*2+3940.7 -> 10023.56 | D13: =sum(1790.93,2240.98,1841.82) -> 5873.73 | E13: =sum(375.41*3,110.41*3) -> 1457.46 | F13: =sum(B13:E13) -> 17470.73
A14: DEC | B14: =sum(122.96,1.15) -> 124.11 | C14: =sum(2776.47,2240.59) -> 5017.06 | D14: =sum(2124,1866.68) -> 3990.68 | E14: =sum(375.41*2,110.41*2) -> 971.64 | F14: =sum(B14:E14) -> 10103.49
C17: =sum(3708.07*6+4089.41*4+5520.7+3680.47+2862.59+4089*11+882.75*2) -> 97414.32

Sheet 2022
B1: Expense | C1: Income | D1: Net Profit | E1: Transport | F1: Living | G1: Bill | H1: Groceries | I1: Dine | J1: RMIT | K1: Mortgage | L1: Childcare
B2: =SUM(E2:L2) -> -109743.72 | C2: =SUM(C3:C14) -> 134817.67 | D2: =SUM(B2,C2) -> 25073.95 | E2: =SUM(E15:E1014) -> -1739.21 | F2: =SUM(F15:F1014) -> -24361.52 | G2: =SUM(G15:G1014) -> -14890.06 | H2: =SUM(H15:H1014) -> -8937.41 | I2: =SUM(I15:I1014) -> -4814.67 | J2: =SUM(J15:J1014) -> -26545 | K2: =SUM(K15:K1014) -> -24340 | L2: =SUM(L15:L1014) -> -4115.85
A3: 44562 | B3: =SUM(E3:L3) -> -5045.13 | C3: ='2022_income'!F3 -> 10557.88 | D3: =SUM(B3,C3) -> 5512.75 | E3: =sum(E15:E45) -> -338.45 | F3: =sum(F15:F45) -> -813.08 | G3: =sum(G15:G45) -> -201.19 | H3: =sum(H15:H45) -> -1230.37 | I3: =sum(I15:I45) -> -350.93 | J3: =sum(J15:J45) -> 0 | K3: =sum(K15:K45) -> -1883 | L3: =sum(L15:L45) -> -228.11
A4: 44593 | B4: =SUM(E4:L4) -> -4644.96 | C4: ='2022_income'!F4 -> 8373.77 | D4: =SUM(B4,C4) -> 3728.81 | E4: =SUM(E46:E73) -> -384.43 | F4: =SUM(F46:F73) -> -434.69 | G4: =SUM(G46:G73) -> -385.33 | H4: =SUM(H46:H73) -> -988.27 | I4: =SUM(I46:I73) -> -365.68 | J4: =SUM(J46:J73) -> 0 | K4: =SUM(K46:K73) -> -1883 | L4: =SUM(L46:L73) -> -203.56
A5: 44621 | B5: =SUM(E5:L5) -> -7774.84 | C5: ='2022_income'!F5 -> 11850.93 | D5: =SUM(B5,C5) -> 4076.09 | E5: =sum(E74:E104) -> -414.24 | F5: =sum(F74:F104) -> -1665.07 | G5: =sum(G74:G104) -> -1864.71 | H5: =sum(H74:H104) -> -1151.24 | I5: =sum(I74:I104) -> -507.76 | J5: =sum(J74:J104) -> 0 | K5: =sum(K74:K104) -> -1889 | L5: =sum(L74:L104) -> -282.82
A6: 44652 | B6: =SUM(E6:L6) -> -5793.35 | C6: ='2022_income'!F6 -> 9846.13 | D6: =SUM(B6,C6) -> 4052.78 | E6: =sum(E105:E134) -> -112.65 | F6: =sum(F105:F134) -> -1657.91 | G6: =sum(G105:G134) -> -439.93 | H6: =sum(H105:H134) -> -696.43 | I6: =sum(I105:I134) -> -786.23 | J6: =sum(J105:J134) -> 0 | K6: =sum(K105:K134) -> -1889 | L6: =sum(L105:L134) -> -211.2
A7: 44682 | B7: =SUM(E7:L7) -> -4398.68 | C7: ='2022_income'!F7 -> 9554.11 | D7: =SUM(B7,C7) -> 5155.43 | E7: =sum(E135:E165) -> -20 | F7: =sum(F135:F165) -> -442.93 | G7: =sum(G135:G165) -> -864.25 | H7: =sum(H135:H165) -> -452.94 | I7: =sum(I135:I165) -> -518.36 | J7: =sum(J135:J165) -> 0 | K7: =sum(K135:K165) -> -1889 | L7: =sum(L135:L165) -> -211.2
A8: 44713 | B8: =SUM(E8:L8) -> -9688.97 | C8: ='2022_income'!F8 -> 12136.95 | D8: =SUM(B8,C8) -> 2447.98 | E8: =sum(E166:E195) -> -78.75 | F8: =sum(F166:F195) -> -6685.75 | G8: =sum(G166:G195) -> -343.97 | H8: =sum(H166:H195) -> -418.28 | I8: =sum(I166:I195) -> -62.02 | J8: =sum(J166:J195) -> 0 | K8: =sum(K166:K195) -> -1889 | L8: =sum(L166:L195) -> -211.2
A9: 44743 | B9: =SUM(E9:L9) -> -22955.03 | C9: ='2022_income'!F9 -> 18385.52 | D9: =SUM(B9,C9) -> -4569.51 | E9: =sum(E196:E226) -> -67.6 | F9: =sum(F196:F226) -> -1156.13 | G9: =sum(G196:G226) -> -3675.52 | H9: =sum(H196:H226) -> -593.64 | I9: =sum(I196:I226) -> -281.94 | J9: =sum(J196:J226) -> -14545 | K9: =sum(K196:K226) -> -2284 | L9: =sum(L196:L226) -> -351.2
A10: 44774 | B10: =SUM(E10:L10) -> -11976.91 | C10: ='2022_income'!F10 -> 12238.99 | D10: =SUM(B10,C10) -> 262.08 | E10: =sum(E227:E257) -> -62.64 | F10: =sum(F227:F257) -> -4501.84 | G10: =sum(G227:G257) -> -3723.01 | H10: =sum(H227:H257) -> -987.84 | I10: =sum(I227:I257) -> -367.14 | J10: =sum(J227:J257) -> 0 | K10: =sum(K227:K257) -> -1889 | L10: =sum(L227:L257) -> -445.44
A11: 44805 | B11: =SUM(E11:L11) -> -6346.19 | C11: ='2022_income'!F11 -> 9561.5 | D11: =SUM(B11,C11) -> 3215.31 | E11: =SUM(E258:E287) -> -10 | F11: =SUM(F258:F287) -> -1581.72 | G11: =SUM(G258:G287) -> -673.74 | H11: =SUM(H258:H287) -> -935.85 | I11: =SUM(I258:I287) -> -570.97 | J11: =SUM(J258:J287) -> 0 | K11: =SUM(K258:K287) -> -1935 | L11: =SUM(L258:L287) -> -638.91
A12: 44835 | B12: =SUM(E12:L12) -> -5861.75 | C12: ='2022_income'!F12 -> 10052.65 | D12: =SUM(B12,C12) -> 4190.9 | E12: =SUM(E288:E318) -> -81.3 | F12: =SUM(F288:F318) -> -1369.52 | G12: =SUM(G288:G318) -> -905.01 | H12: =SUM(H288:H318) -> -569.33 | I12: =SUM(I288:I318) -> -497.18 | J12: =SUM(J288:J318) -> 0 | K12: =SUM(K288:K318) -> -1935 | L12: =SUM(L288:L318) -> -504.41
A13: 44866 | B13: =SUM(E13:L13) -> -9053.85 | C13: ='2022_income'!F13 -> 12852 | D13: =SUM(B13,C13) -> 3798.15 | E13: =SUM(E319:E348) -> -49.15 | F13: =SUM(F319:F348) -> -2942.42 | G13: =SUM(G319:G348) -> -964.37 | H13: =SUM(H319:H348) -> -339.25 | I13: =SUM(I319:I348) -> -392.26 | J13: =SUM(J319:J348) -> -2000 | K13: =SUM(K319:K348) -> -1935 | L13: =SUM(L319:L348) -> -431.4
A14: 44896 | B14: =SUM(E14:L14) -> -16204.06 | C14: ='2022_income'!F14 -> 9407.24 | D14: =SUM(B14,C14) -> -6796.82 | E14: =SUM(E349:E379) -> -120 | F14: =SUM(F349:F379) -> -1110.46 | G14: =SUM(G349:G379) -> -849.03 | H14: =SUM(H349:H379) -> -573.97 | I14: =SUM(I349:I379) -> -114.2 | J14: =SUM(J349:J379) -> -10000 | K14: =SUM(K349:K379) -> -3040 | L14: =SUM(L349:L379) -> -396.4
A15: 44562 | E15: -5 | F15: =-sum(15,17.97,50.64) -> -83.61 | I15: -27.2
A16: 44563 | F16: =-sum(17.97,50.64) -> -68.61 | H16: =-sum(35.75) -> -35.75 | I16: =-sum(9.9,27.2) -> -37.1
A17: 44564 | H17: =-sum(4.5,32.55,20.56) -> -57.61 | I17: -12.45
A18: 44565 | E18: -39.48 | F18: =-sum(44.09) -> -44.09
A19: 44566 | F19: -25.6 | H19: =-sum(12.21,13.5) -> -25.71
A20: 44567 | E20: -5 | F20: =-sum(9) -> -9 | G20: -29.17 | H20: =-sum(31.44,28.42) -> -59.86 | I20: =-sum(29.8,8.6) -> -38.4 | K20: =-sum(498,1385) -> -1883
A21: 44568 | B21: =AVERAGE(B3:B7) -> -5531.392 | E21: -44.17 | F21: -26.5 | H21: -18.16 | L21: -41
A22: 44569 | H22: =-sum(2.6,13.73,11.2) -> -27.53 | I22: =-sum(14.72,42) -> -56.72
A23: 44570 | F23: =-sum(29,22.99) -> -51.99 | I23: =-sum(40.4,9.9) -> -50.3
A24: 44571 | E24: -50.16 | F24: =-sum(57,23,22) -> -102 | G24: -33.5 | H24: =-sum(29.68,15,41.52) -> -86.2 | I24: -19.5
A25: 44572
A26: 44573
A27: 44574 | H27: =-sum(17.57,3.09) -> -20.66 | I27: -4.2
A28: 44575 | F28: -76.67 | H28: =-sum(106.38) -> -106.38 | L28: -41
A29: 44576 | H29: =-sum(49.5,3.1) -> -52.6 | I29: =-sum(42,3.9) -> -45.9
A30: 44577 | E30: -61.54 | F30: =-sum(103,43.54) -> -146.54 | H30: -20.5 | I30: -8.2
A31: 44578 | H31: =-sum(49.36,27.35,111.5) -> -188.21
A32: 44579 | L32: -84.61
A33: 44580 | E33: -50.46 | H33: =-sum(5.81,4.8,9,6.3) -> -25.91
A34: 44581 | H34: =-sum(8.75,5.67) -> -14.42
A35: 44582 | F35: -20.5 | H35: =-sum(14.32,50.49) -> -64.81 | I35: =-sum(3,28) -> -31 | L35: -41
A36: 44583 | E36: -30 | I36: -19.96
A37: 44584 | E37: -52.64 | F37: -12.5 | H37: =-sum(120.31,54,48.62,9.08) -> -232.01
A38: 44585 | G38: =-sum(33.5,40.03) -> -73.53
A39: 44586 | F39: =-sum(133,12.47) -> -145.47 | G39: -64.99
A40: 44587 | H40: -58.05
A41: 44588 | H41: -61
A42: 44589 | L42: -20.5
A43: 44590
A44: 44591 | H44: -75
A45: 44592
A46: 44593 | G46: -107.54 | L46: -19.59
A47: 44594
A48: 44595
A49: 44596 | F49: -24.09 | G49: -76.6 | L49: -41
A50: 44597 | F50: =-sum(2.23,115.48) -> -117.71 | H50: =-sum(39.7,17.5,25) -> -82.2 | I50: =-sum(40.4,8,30) -> -78.4
A51: 44598 | E51: -39.44 | F51: -2.8 | H51: =-sum(17.62,14.59,37.5,86.52) -> -156.23 | I51: -14.98 | K51: =-sum(498,1385) -> -1883
A52: 44599 | G52: -33.5
A53: 44600 | G53: -29.17 | H53: =-sum(19.6,29.78,13.76) -> -63.14
A54: 44601 | E54: -55.85 | H54: -22.5
A55: 44602 | H55: =-sum(8.8,35.8) -> -44.6 | I55: -26
A56: 44603 | F56: -3.1 | H56: =-sum(9.43) -> -9.43 | L56: -41
A57: 44604 | I57: -37.7
A58: 44605 | H58: =-sum(49.24,59.24) -> -108.48
A59: 44606 | F59: =-sum(61,29) -> -90
A60: 44607 | E60: -54.42 | F60: -27 | H60: =-sum(5.5,28.01,21.78,5.99,55.3) -> -116.58
A61: 44608 | H61: =-sum(32.61) -> -32.61 | I61: -75.93
A62: 44609 | E62: -56.23 | F62: -30 | H62: =-sum(25.4,11) -> -36.4
A63: 44610 | E63: -20 | H63: -5.5 | L63: -41.07
A64: 44611 | H64: -4 | I64: -13.5
A65: 44612 | H65: =-sum(20) -> -20
A66: 44613 | F66: =-sum(4.9,36) -> -40.9 | G66: -33.5 | H66: =-sum(52.25,42.54,43.16) -> -137.95 | I66: =-sum(38,7.27) -> -45.27
A67: 44614 | E67: -54.62 | G67: =-sum(64.99,40.03) -> -105.02 | H67: =-sum(27.44,14.8,9.6) -> -51.84
A68: 44615 | E68: -31.94
A69: 44616 | E69: -45.85 | H69: -29.36
A70: 44617 | F70: -69 | H70: =-sum(4,9.95) -> -13.95 | I70: -33.5 | L70: -60.9
A71: 44618 | E71: -26.08 | F71: -3.1
A72: 44619 | F72: -26.99 | H72: =-sum(9.05,3.89,2.7) -> -15.64 | I72: -40.4
A73: 44620 | H73: =-sum(18.7,19.16) -> -37.86
A74: 44621 | E74: -2.38 | F74: -114.56 | H74: =-sum(51.39) -> -51.39 | L74: -41.71
A75: 44622 | F75: -399 | H75: -3.9 | I75: -3.2
A76: 44623 | E76: -51.26 | F76: -13 | I76: -34
A77: 44624 | L77: -41
A78: 44625 | F78: =-sum(3.1) -> -3.1 | H78: =-sum(15.33,6.45) -> -21.78
A79: 44626 | F79: =-sum(14.99,45.76) -> -60.75 | H79: =-sum(5.1,9.7,14.99,6.49) -> -36.28 | I79: -39.5
A80: 44627 | E80: -10 | F80: =-sum(25.95,29,24.99) -> -79.94 | G80: -33.5 | H80: -140.72 | I80: -73.73 | K80: =-sum(504,1385) -> -1889
A81: 44628 | E81: -51.09 | F81: =-sum(24,28.95,55.87) -> -108.82 | G81: -29.17 | H81: =-sum(12.6,46.5,11.9,26.62) -> -97.62
A82: 44629 | F82: =-sum(27.3,10,0.32) -> -37.62
A83: 44630
A84: 44631 | E84: -56.54 | I84: -53.5 | L84: -52.8
A85: 44632 | H85: =-sum(36.38,29.69,53.2,11) -> -130.27
A86: 44633 | F86: -12.4 | H86: -32 | I86: -13.5
A87: 44634 | F87: =-sum(38.15) -> -38.15 | H87: -65.45 | I87: -45.82
A88: 44635 | E88: -49.63 | F88: -3 | H88: =-sum(8.9,60.05,15.95,8.99,27.79,9.9) -> -131.58
A89: 44636 | F89: =-sum(19.96,72) -> -91.96 | H89: -16.74 | I89: -10.15 | L89: -41.71
A90: 44637
A91: 44638 | E91: -71.2 | F91: =-sum(48,20) -> -68 | I91: =-sum(2,46) -> -48 | L91: -52.8
A92: 44639 | G92: -1532.8 | I92: -57.58
A93: 44640 | F93: =-sum(25.9,156,37.5) -> -219.4 | H93: =-sum(16.64,23.52,7.83,9,33.56) -> -90.55 | I93: =-sum(15.3,18) -> -33.3
A94: 44641 | F94: =-sum(2,5,16.45,19.9) -> -43.35 | G94: -33.5 | H94: =-sum(12.9,3.5) -> -16.4
A95: 44642 | E95: -63.19 | F95: -46.75 | G95: -40.03
A96: 44643 | F96: -69 | H96: =-sum(11.45,1.01,109.98,25.45) -> -147.89
A97: 44644 | F97: -14.5 | G97: -67.72 | H97: =-sum(26.2,12.72,47.35) -> -86.27 | I97: =-sum(7.5,4.28) -> -11.78
A98: 44645 | G98: -64.99 | H98: -8.57 | L98: -52.8
A99: 44646 | E99: =-sum(53.58,5.37) -> -58.95 | F99: =-sum(37.8,38.97) -> -76.77 | H99: =-sum(8.75,25.3) -> -34.05 | I99: -17
A100: 44647 | F100: =-sum(10) -> -10 | H100: =-sum(2.07,11.49,13.37) -> -26.93 | I100: =-sum(11.8,33) -> -44.8
...

Sheet 2022_income
B1: interest | C1: Will | D1: Yan | E1: Salary Package
B2: =sum(B3:B1000) -> 0 | C2: =sum(C3:C1000) -> 66651.62 | D2: =sum(D3:D1000) -> 54345.61 | E2: =sum(E3:E1000) -> 13820.44
A3: JAN | C3: =sum(923.16,1131.25*2,74.76*2,974.35,50.98,450,15.03) -> 4825.54 | D3: =sum(2010.14,25,1663.2,450,0.52,28.72) -> 4177.58 | E3: =sum(56.09,506.96,563.24,428.47) -> 1554.76 | F3: =sum(B3:E3) -> 10557.88
A4: Feb | C4: =sum(302.71,1131.25*2,74.76*2,644.63) -> 3359.36 | D4: =sum(1398.72,1646.21,1.04) -> 3045.97 | E4: =sum(563.24,563.24,841.96) -> 1968.44 | F4: =sum(B4:E4) -> 8373.77
A5: MAR | C5: =sum(903.86,1131.25,74.76,753.87,1122.25,74.76) -> 4060.75 | D5: =sum(1499.71,0.52,31.12,609.94,1724.2,1625.03) -> 5490.52 | E5: =sum(563.24,609.94,56.09,507.15,563.24) -> 2299.66 | F5: =sum(B5:E5) -> 11850.93
A6: APR | C6: =sum(2632.08*2,74.76*2) -> 5413.68 | D6: =sum(1559.42,2179.97) -> 3739.39 | E6: =sum(346.53,56.09,290.44) -> 693.06 | F6: =sum(B6:E6) -> 9846.13
A7: MAY | C7: =sum(2632.08*2,74.76*2) -> 5413.68 | D7: =sum(54.5,18.95,1645.01,1728.91) -> 3447.37 | E7: =sum(346.53,346.53) -> 693.06 | F7: =sum(B7:E7) -> 9554.11
A8: JUN | C8: =sum(2632.08,74.76*3,2677.26*2) -> 8210.88 | D8: =sum(1543.92,1689.09) -> 3233.01 | E8: =sum(346.53,346.53) -> 693.06 | F8: =sum(B8:E8) -> 12136.95
A9: JUL | C9: =sum(2677.26*2,10.68) -> 5365.2 | D9: =sum(1931.09,1540.69,8855.48) -> 12327.26 | E9: =sum(346.53,346.53) -> 693.06 | F9: =sum(B9:E9) -> 18385.52
A10: AUG | C10: =sum(2677.26*2) -> 5354.52 | D10: =sum(1814.29,1451.42,2366.46) -> 5632.17 | E10: =sum(346.53,346.53,145.62,67.09,346.53) -> 1252.3 | F10: =sum(B10:E10) -> 12238.99
A11: SEP | C11: =sum(2677.26)*2 -> 5354.52 | D11: =sum(1463.94,1749.78) -> 3213.72 | E11: =sum(154.57,342.06,342.06,154.57) -> 993.26 | F11: =sum(B11:E11) -> 9561.5
A12: OCT | C12: =sum(2677.26)*2 -> 5354.52 | D12: =sum(2337.59,1367.28) -> 3704.87 | E12: =sum(342.06*2,154.57*2) -> 993.26 | F12: =sum(B12:E12) -> 10052.65
A13: NOV | C13: =sum(2677.26*2,3229.93) -> 8584.45 | D13: =sum(1677.03,1597.26) -> 3274.29 | E13: =sum(342.06,154.57,342.06,154.57) -> 993.26 | F13: =sum(B13:E13) -> 12852
A14: DEC | C14: =sum(2677.26)*2 -> 5354.52 | D14: =sum(1524.43,1535.03) -> 3059.46 | E14: =sum(342.06,154.57,342.06,154.57) -> 993.26 | F14: =sum(B14:E14) -> 9407.24

Sheet 2021
B1: Expense | C1: Income | D1: Net Profit | E1: Transport | F1: Living | G1: Bill | H1: License | I1: RMIT | J1: Autumn | K1: Baby
B2: =SUM(E2:K2) -> -76368.21 | C2: =SUM('2021_income'!B2) -> 91685.03 | D2: =SUM(B2,C2) -> 15316.82 | E2: =SUM(E15:E1014) -> -5119.05 | F2: =SUM(F15:F1014) -> -22627.63 | G2: =SUM(G15:G1014) -> -27625.23 | H2: =SUM(H15:H1014) -> -1036.77 | I2: =SUM(I15:I1014) -> -17582.38 | J2: =SUM(J15:J1014) -> -1069.27 | K2: =SUM(K15:K1014) -> -1307.88
A3: 44197 | B3: =sum(E15:K45) -> -4546.05 | C3: ='2021_income'!B3 -> 4787.32 | D3: =SUM(B3,C3) -> 241.27 | E3: =sum(E15:E45) -> -1159.4 | F3: =sum(F15:F45) -> -1264.88 | G3: =sum(G15:G45) -> -1792.37 | H3: =sum(H15:H45) -> 0 | I3: =sum(I15:I45) -> 0 | J3: =sum(J15:J45) -> -34.99 | K3: =sum(K15:K45) -> -294.41
A4: 44228 | B4: =sum(E46:K73) -> -4022.84 | C4: ='2021_income'!B4 -> 5244.63 | D4: =SUM(B4,C4) -> 1221.79 | E4: =sum(E46:E73) -> -396.44 | F4: =sum(F46:F73) -> -1326.44 | G4: =sum(G46:G73) -> -1270 | H4: =sum(H46:H73) -> 0 | I4: =sum(I46:I73) -> -825 | J4: =sum(J46:J73) -> -38.99 | K4: =sum(K46:K73) -> -165.97
A5: 44256 | B5: =sum(E74:K104) -> -9522.24 | C5: ='2021_income'!B5 -> 6870.83 | D5: =SUM(B5,C5) -> -2651.41 | E5: =sum(E74:E104) -> -236.24 | F5: =sum(F74:F104) -> -1548.73 | G5: =sum(G74:G104) -> -2768.4 | H5: =sum(H74:H104) -> 0 | I5: =sum(I74:I104) -> -4547.96 | J5: =sum(J74:J104) -> -236.93 | K5: =sum(K74:K104) -> -183.98
A6: 44287 | B6: =sum(E105:K134) -> -3484.77 | C6: ='2021_income'!B6 -> 4899.62 | D6: =SUM(B6,C6) -> 1414.85 | E6: =sum(E105:E134) -> -253.32 | F6: =sum(F105:F134) -> -1742.11 | G6: =sum(G105:G134) -> -1303.5 | H6: =sum(H105:H134) -> 0 | I6: =sum(I105:I134) -> 0 | J6: =sum(J105:J134) -> -63.45 | K6: =sum(K105:K134) -> -122.39
A7: 44317 | B7: =sum(E135:K165) -> -4418.27 | C7: ='2021_income'!B7 -> 5290.61 | D7: =SUM(B7,C7) -> 872.34 | E7: =sum(E135:E165) -> -182.92 | F7: =sum(F135:F165) -> -1349.17 | G7: =sum(G135:G165) -> -2080 | H7: =sum(H135:H165) -> -190.87 | I7: =sum(I135:I165) -> 0 | J7: =sum(J135:J165) -> -357.63 | K7: =sum(K135:K165) -> -257.68
A8: 44348 | B8: =sum(E166:K195) -> -4732.87 | C8: ='2021_income'!B8 -> 2717.1 | D8: =SUM(B8,C8) -> -2015.77 | E8: =sum(E166:E195) -> -99.38 | F8: =sum(F166:F195) -> -1561.7 | G8: =sum(G166:G195) -> -1347.2 | H8: =sum(H166:H195) -> 0 | I8: =sum(I166:I195) -> -1506.14 | J8: =sum(J166:J195) -> 0 | K8: =sum(K166:K195) -> -218.45
A9: 44378 | B9: =sum(E196:K226) -> -9434.34 | C9: ='2021_income'!B9 -> 9980.34 | D9: =SUM(B9,C9) -> 546 | E9: =sum(E196:E226) -> -227.07 | F9: =sum(F196:F226) -> -1932.29 | G9: =sum(G196:G226) -> -3162.34 | H9: =sum(H196:H226) -> 0 | I9: =sum(I196:I226) -> -4073.94 | J9: =sum(J196:J226) -> -38.7 | K9: =sum(K196:K226) -> 0
A10: 44409 | B10: =sum(E227:K257) -> -9442.08 | C10: ='2021_income'!B10 -> 8090.33 | D10: =SUM(B10,C10) -> -1351.75 | E10: =sum(E227:E257) -> -279.96 | F10: =sum(F227:F257) -> -1972.41 | G10: =sum(G227:G257) -> -2487.87 | H10: =sum(H227:H257) -> 0 | I10: =sum(I227:I257) -> -4547.04 | J10: =sum(J227:J257) -> -113.8 | K10: =sum(K227:K257) -> -41
A11: 44440 | B11: =sum(E258:K287) -> -6645.2 | C11: ='2021_income'!B11 -> 10360.59 | D11: =SUM(B11,C11) -> 3715.39 | E11: =sum(E258:E287) -> -219.48 | F11: =sum(F258:F287) -> -1831.98 | G11: =sum(G258:G287) -> -2522.74 | H11: =sum(H258:H287) -> 0 | I11: =sum(I258:I287) -> -1999 | J11: =sum(J258:J287) -> -72 | K11: =sum(K258:K287) -> 0
A12: 44470 | B12: =sum(E288:K318) -> -7835.09 | C12: ='2021_income'!B12 -> 9938.69 | D12: =SUM(B12,C12) -> 2103.6 | E12: =sum(E288:E318) -> -1248.28 | F12: =sum(F288:F318) -> -2774.25 | G12: =sum(G288:G318) -> -3592.48 | H12: =sum(H288:H318) -> 0 | I12: =sum(I288:I318) -> -83.3 | J12: =sum(J288:J318) -> -112.78 | K12: =sum(K288:K318) -> -24
A13: 44501 | B13: =sum(E319:K348) -> -6716.28 | C13: ='2021_income'!B13 -> 12165.04 | D13: =SUM(B13,C13) -> 5448.76 | E13: =sum(E319:E348) -> -393.05 | F13: =sum(F319:F348) -> -2927.56 | G13: =sum(G319:G348) -> -2549.77 | H13: =sum(H319:H348) -> -845.9 | I13: =sum(I319:I348) -> 0 | J13: =sum(J319:J348) -> 0 | K13: =sum(K319:K348) -> 0
A14: 44531 | B14: =sum(E349:K379) -> -5568.18 | C14: ='2021_income'!B14 -> 11339.93 | D14: =SUM(B14,C14) -> 5771.75 | E14: =sum(E349:E379) -> -423.51 | F14: =sum(F349:F379) -> -2396.11 | G14: =sum(G349:G379) -> -2748.56 | H14: =sum(H349:H379) -> 0 | I14: =sum(I349:I379) -> 0 | J14: =sum(J349:J379) -> 0 | K14: =sum(K349:K379) -> 0
A15: 44197 | C15: ='2021_income'!B15 | G15: -70
A16: 44198 | C16: ='2021_income'!B16 | F16: -50.8
A17: 44199 | C17: ='2021_income'!B17 | F17: =-sum(44.2,49,8.3,19.95) -> -121.45 | J17: -34.99
A18: 44200 | C18: ='2021_income'!B18 | F18: 10 | G18: -600
A19: 44201 | C19: ='2021_income'!B19 | F19: =-sum(5,14.95,85.92) -> -105.87
A20: 44202 | C20: ='2021_income'!B20 | F20: =-sum(4.95,4.95,7.99,4.15) -> -22.04
A21: 44203 | C21: ='2021_income'!B21 | F21: =-sum(35.45,13.67,12.45,6.87,10.9,30,-3) -> -106.34
A22: 44204 | C22: ='2021_income'!B22 | F22: =-sum(17.95) -> -17.95 | K22: =-sum(37.48,190) -> -227.48
A23: 44205 | C23: ='2021_income'!B23 | F23: =-sum(4.95,26.24,47.56) -> -78.75 | K23: =-9.5*2 -> -19
A24: 44206 | C24: ='2021_income'!B24 | F24: =-sum(12,20,25.9) -> -57.9
A25: 44207 | C25: ='2021_income'!B25 | E25: -20 | F25: =-sum(6.5) -> -6.5 | K25: 87.36
A26: 44208 | C26: ='2021_income'!B26 | E26: -960 | F26: -52.33
A27: 44209 | C27: ='2021_income'!B27 | E27: -37.29 | F27: =-sum(45,18.88) -> -63.88
A28: 44210 | C28: ='2021_income'!B28 | F28: =-sum(6.95,18.93,8.49,9.33) -> -43.7
A29: 44211 | C29: ='2021_income'!B29 | F29: =-sum(14.3) -> -14.3
A30: 44212 | C30: ='2021_income'!B30 | F30: =-sum(19.05,2.5) -> -21.55 | G30: =-sum(186.66,335.71) -> -522.37
A31: 44213 | C31: ='2021_income'!B31 | F31: =-sum(36.34,32,25.35) -> -93.69
A32: 44214 | C32: ='2021_income'!B32 | F32: =-sum(0.7) -> -0.7 | G32: -600 | K32: -35.8
A33: 44215 | C33: ='2021_income'!B33 | E33: =-sum(9,14) -> -23 | F33: =-sum(10.63,12.5,34.8) -> -57.93
A34: 44216 | C34: ='2021_income'!B34 | E34: -61.84 | F34: =-sum(5,4.95,12.24,-27.94,54.38) -> -48.63
A35: 44217 | C35: ='2021_income'!B35 | F35: =-sum(14.3,16.8) -> -31.1
A36: 44218 | C36: ='2021_income'!B36
A37: 44219 | C37: ='2021_income'!B37 | F37: -24
A38: 44220 | C38: ='2021_income'!B38 | F38: =-sum(6,9.9) -> -15.9
A39: 44221 | C39: ='2021_income'!B39 | F39: -38.07
A40: 44222 | C40: ='2021_income'!B40 | F40: =-sum(5.2) -> -5.2
A41: 44223 | C41: ='2021_income'!B41
A42: 44224 | C42: ='2021_income'!B42 | E42: -53.27 | F42: 40.27 | K42: -95
A43: 44225 | C43: ='2021_income'!B43 | E43: -4 | F43: =-sum(36.23,7.15) -> -43.38 | K43: -4.49
A44: 44226 | C44: ='2021_income'!B44 | F44: =-sum(10,23.6) -> -33.6
A45: 44227 | C45: ='2021_income'!B45 | F45: =-sum(3.8,9.33,146.46) -> -159.59
A46: 44228 | C46: ='2021_income'!B46 | F46: =-sum(60.05,21.8) -> -81.85 | G46: =-sum(70,600) -> -670
A47: 44229 | C47: ='2021_income'!B47 | F47: =-sum(4.9,30.69,3.8,3.95,6.55) -> -49.89 | J47: -38.99
A48: 44230 | C48: ='2021_income'!B48
A49: 44231 | C49: ='2021_income'!B49
A50: 44232 | C50: ='2021_income'!B50 | F50: =-sum(135,10,10.61,27.41,9.22,9) -> -201.24 | K50: -70.97
A51: 44233 | C51: ='2021_income'!B51 | E51: =-sum(268,51.77) -> -319.77 | F51: =-sum(50,4.9) -> -54.9
A52: 44234 | C52: ='2021_income'!B52 | F52: =-sum(29.28,14.45,5.05) -> -48.78
A53: 44235 | C53: ='2021_income'!B53 | F53: =-sum(21.17,8,9.99) -> -39.16
A54: 44236 | C54: ='2021_income'!B54 | F54: =-sum(2.3,3.3,2.5,6.4) -> -14.5
A55: 44237 | C55: ='2021_income'!B55 | F55: =-sum(4.9,24.5,36.21,8.8) -> -74.41
A56: 44238 | C56: ='2021_income'!B56
A57: 44239 | C57: ='2021_income'!B57 | F57: =-sum(4.9,5.9,33.35,5.48,13.03) -> -62.66
A58: 44240 | C58: ='2021_income'!B58
A59: 44241 | C59: ='2021_income'!B59
A60: 44242 | C60: ='2021_income'!B60 | F60: =-sum(7.46,6.75,3.5,36,5.5) -> -59.21 | G60: -600
A61: 44243 | C61: ='2021_income'!B61 | E61: -46.61
A62: 44244 | C62: ='2021_income'!B62 | F62: =-sum(2.5,9) -> -11.5
A63: 44245 | C63: ='2021_income'!B63 | F63: -10.6
A64: 44246 | C64: ='2021_income'!B64 | F64: =-sum(34.28,4.9,2,14.44,21.23,5.6) -> -82.45
A65: 44247 | C65: ='2021_income'!B65 | F65: =-sum(20.02,29.89) -> -49.91
A66: 44248 | C66: ='2021_income'!B66 | F66: =-sum(10.39,6.9,2.5,22.4,42.69) -> -84.88
A67: 44249 | C67: ='2021_income'!B67 | F67: =-sum(12.5,4.15,12.32) -> -28.97
A68: 44250 | C68: ='2021_income'!B68 | F68: =-sum(36,70.67) -> -106.67
A69: 44251 | C69: ='2021_income'!B69 | F69: =-sum(13,7.15,12.32,35.2,14,33.14) -> -114.81
A70: 44252 | C70: ='2021_income'!B70 | E70: -30.06 | F70: =-sum(21,7.75) -> -28.75 | K70: -95
A71: 44253 | C71: ='2021_income'!B71 | F71: =-sum(13.8,8.15,17) -> -38.95
A72: 44254 | C72: ='2021_income'!B72 | F72: =-sum(23.8,20,5) -> -48.8 | I72: -825
A73: 44255 | C73: ='2021_income'!B73 | F73: =-sum(18.55,15) -> -33.55
A74: 44256 | C74: ='2021_income'!B74 | F74: =-sum(35.25,5) -> -40.25 | G74: =-sum(600,70,184.77) -> -854.77
A75: 44257 | C75: ='2021_income'!B75 | F75: =-sum(25,34.71,5.8) -> -65.51
A76: 44258 | C76: ='2021_income'!B76 | E76: -20 | F76: =-sum(3.85,3.23,12.5,6.46,-25,25.8) -> -26.84 | G76: -111.63
A77: 44259 | C77: ='2021_income'!B77 | F77: =-sum(4.4,18.7) -> -23.1 | J77: -26.94
A78: 44260 | C78: ='2021_income'!B78 | F78: =-sum(4.9,4.26,4.5,1.8,-39.82) -> 24.36 | G78: -152 | J78: -38.99
A79: 44261 | C79: ='2021_income'!B79 | E79: -63.92 | F79: -10.6
A80: 44262 | C80: ='2021_income'!B80 | F80: =-sum(27.02,2.9) -> -29.92
A81: 44263 | C81: ='2021_income'!B81 | F81: 20
A82: 44264 | C82: ='2021_income'!B82 | F82: =-sum(13.4,6.9,25.6) -> -45.9
A83: 44265 | C83: ='2021_income'!B83 | E83: -2.37 | F83: =-sum(32.7,400.99,9.9) -> -443.59
A84: 44266 | C84: ='2021_income'!B84 | G84: -450
A85: 44267 | C85: ='2021_income'!B85 | F85: =-sum(8.95,18.16,2.8) -> -29.91
A86: 44268 | C86: ='2021_income'!B86 | E86: -20 | F86: -15
A87: 44269 | C87: ='2021_income'!B87
A88: 44270 | C88: ='2021_income'!B88 | F88: =-sum(11,42) -> -53 | G88: -600
A89: 44271 | C89: ='2021_income'!B89 | E89: -54.6 | F89: =-sum(3.63,-10.4) -> 6.77
A90: 44272 | C90: ='2021_income'!B90 | F90: =-sum(4,6.5,19.81,1.62,7.04) -> -38.97
A91: 44273 | C91: ='2021_income'!B91 | F91: =-sum(27.05,43.83,54.55) -> -125.43 | K91: -50
A92: 44274 | C92: ='2021_income'!B92 | F92: -29.13
A93: 44275 | C93: ='2021_income'!B93 | F93: =-sum(19.35) -> -19.35 | J93: -41
A94: 44276 | C94: ='2021_income'!B94
A95: 44277 | C95: ='2021_income'!B95 | E95: -2.84 | F95: =-sum(18,11.38,12,61.98,13) -> -116.36
A96: 44278 | C96: ='2021_income'!B96 | E96: -40.8 | F96: =-sum(19.66) -> -19.66 | J96: -130
A97: 44279 | C97: ='2021_income'!B97 | F97: =-sum(8.08,23.3,9.99,9.6) -> -50.97 | K97: -8.98
A98: 44280 | C98: ='2021_income'!B98 | F98: =-sum(16.75,51) -> -67.75 | I98: -4547.96 | K98: -95
A99: 44281 | C99: ='2021_income'!B99 | F99: =-sum(8.6,13.5,51) -> -73.1
A100: 44282 | C100: ='2021_income'!B100 | F100: =-sum(24.5,6.6,28,5) -> -64.1
...

Sheet 2021_income
B1: INCOME | C1: interest | D1: Will | E1: Yan | F1: Salary Package | H1: Monthly balance
B2: =sum(C2:F2) -> 91685.03 | C2: =sum(C3:C1000) -> 738.75 | D2: =sum(D3:D1000) -> 45855.16 | E2: =sum(E3:E1000) -> 34774.14 | F2: =sum(F3:F1000) -> 10316.98 | H2: =SUM(H3:H1000) -> 91685.03
A3: JAN | B3: =sum(C3:F3) -> 4787.32 | C3: 147.93 | D3: =sum(1160.56,177.57,1455.24,87.22) -> 2880.59 | E3: =sum(388.96*2) -> 777.92 | F3: =490.44*2 -> 980.88 | G3: =E6+F3 -> 3494.23 | H3: =SUM(B3,'2021'!M15) -> 4787.32
A4: Feb | B4: =sum(C4:F4) -> 5244.63 | C4: 129.33 | D4: =sum(1248.97,82.36,842.45,79.52) -> 2253.3 | E4: =sum(767.4,2094.6) -> 2862 | H4: =SUM(B4,'2021'!M16) -> 5244.63
A5: MAR | B5: =sum(C5:F5) -> 6870.83 | C5: 97.26 | D5: =sum(1305.57,250,79.66,879.46,79.66,843.82) -> 3438.17 | E5: =sum(1111.8,1111.8,1111.8) -> 3335.4 | H5: =SUM(B5,'2021'!M17) -> 6870.83 | I5: =H5+4547.96 -> 11418.79
A6: APR | B6: =sum(C6:F6) -> 4899.62 | C6: 114.66 | D6: =sum(79.66,1103.72,15.07,79.66,993.5) -> 2271.61 | E6: =sum(1111.8,261.75,1111.8,28) -> 2513.35 | H6: =SUM(B6,'2021'!M18) -> 4899.62
A7: MAY | B7: =sum(C7:F7) -> 5290.61 | C7: 92.29 | D7: =sum(113.96,1189.68,175.7,1224.99) -> 2704.33 | E7: =sum(1111.8,200,50,1111.8,20.39) -> 2493.99 | H7: =SUM(B7,'2021'!M19) -> 5290.61
A8: JUN | B8: =sum(C8:F8) -> 2717.1 | C8: 114.03 | D8: =sum(175.7,848.77,147.64,189.56,11.92,865.9,174.02,189.56) -> 2603.07 | H8: =SUM(B8,'2021'!M20) -> 2717.1
A9: JUL | B9: =sum(C9:F9) -> 9980.34 | C9: 43.25 | D9: =sum(242.4,982.62,292.05,645.2,450,353.78) -> 2966.05 | E9: =sum(500,6471.04) -> 6971.04 | H9: =SUM(B9,'2021'!M21) -> 9980.34
A10: AUG | B10: =sum(C10:F10) -> 8090.33 | D10: =sum(600,660.18,375,94.69,350,750,861.1,40,750,74.76,750) -> 5305.73 | E10: =sum(888.8,20,1312.75) -> 2221.55 | F10: 563.05 | H10: =SUM(B10,'2021'!M22) -> 8090.33
A11: SEP | B11: =sum(C11:F11) -> 10360.59 | D11: =sum(669.77,750,74.76,750,129.94,47.18,450,750,74.76,750,871.2,750,74.76) -> 6142.37 | E11: =sum(200,1353.09,1539.03) -> 3092.12 | F11: =sum(563.05,563.05) -> 1126.1 | H11: =SUM(B11,'2021'!M23) -> 10360.59
A12: OCT | B12: =sum(C12:F12) -> 9938.69 | D12: =sum(750,873.99,750,750,74.76,1031.1,750) -> 4979.85 | E12: =sum(20.15,1410.55,40.59,1.5,55,1186.95) -> 2714.74 | F12: =sum(563.05,1118,563.05) -> 2244.1 | H12: =SUM(B12,'2021'!M24) -> 9938.69
A13: NOV | B13: =sum(C13:F13) -> 12165.04 | D13: =sum(74.76,450,750,450,527.4,516.63,74.76,320,971.55) -> 4135.1 | E13: =sum(1,450,450,1548.19,450,1.5,320,1284.95,104.5) -> 4610.14 | F13: =sum(998.4,563.05,1190.8,563.05,104.5) -> 3419.8 | H13: =SUM(B13,'2021'!M25) -> 12165.04
A14: DEC | B14: =sum(C14:F14) -> 11339.93 | D14: =sum(1131.25,92.7,74.76,792.71,450,250,1131.25,74.76,971.55,1131.25,74.76) -> 6174.99 | E14: =sum(239.2,1430.75,32.5,1478.4,1.04) -> 3181.89 | F14: =sum(563.05,563.05,856.95) -> 1983.05 | H14: =SUM(B14,'2021'!M26) -> 11339.93

Sheet 2020
B1: Expense | C1: income | D1: Net Profit | E1: Transport | F1: Living | G1: Bill | H1: License | I1: RMIT | J1: Autumn | K1: Baby
B2: =SUM(E2:K2) -> -52363.92 | C2: =SUM('2020_income'!B2) -> 76938.88 | D2: =SUM(B2,C2) -> 24574.96 | E2: =SUM(E15:E1014) -> -1856.36 | F2: =SUM(F15:F1014) -> -19641.63 | G2: =SUM(G15:G1014) -> -11010.34 | H2: =SUM(H15:H1014) -> -1296.8 | I2: =SUM(I15:I1014) -> -9833.97 | J2: =SUM(J15:J1014) -> -2655.91 | K2: =SUM(K15:K1014) -> -6068.91
A3: Jan | B3: =sum(E15:K45) -> -2325.08 | C3: ='2020_income'!B3 -> 5800 | D3: =SUM(B3,C3) -> 3474.92 | E3: =sum(E15:E45) -> -342.31 | F3: =sum(F15:F45) -> -1629.69 | G3: =sum(G15:G45) -> -251.12 | H3: =sum(H15:H45) -> 0 | I3: =sum(I15:I45) -> 0 | J3: =sum(J15:J45) -> -101.96 | K3: =sum(K15:K45) -> 0
A4: Feb | B4: =sum(E46:K73) -> -2238.79 | C4: ='2020_income'!B4 -> 6670.56 | D4: =SUM(B4,C4) -> 4431.77 | E4: =sum(E46:E73) -> -150.3 | F4: =sum(F46:F73) -> -1832.62 | G4: =sum(G46:G73) -> -282.23 | H4: =sum(H46:H73) -> 0 | I4: =sum(I46:I73) -> 0 | J4: =sum(J46:J73) -> -16.5 | K4: =sum(K46:K73) -> 42.86
A5: Mar | B5: =sum(E74:K104) -> -7341.57 | C5: ='2020_income'!B5 -> 6975.52 | D5: =SUM(B5,C5) -> -366.05 | E5: =sum(E74:E104) -> -197.97 | F5: =sum(F74:F104) -> -1361.66 | G5: =sum(G74:G104) -> -751.87 | H5: =sum(H74:H104) -> 0 | I5: =sum(I74:I104) -> -4914.08 | J5: =sum(J74:J104) -> -115.99 | K5: =sum(K74:K104) -> 0
A6: Apr | B6: =sum(E105:K134) -> -2233.24 | C6: ='2020_income'!B6 -> 5752.06 | D6: =SUM(B6,C6) -> 3518.82 | E6: =sum(E105:E134) -> -124.18 | F6: =sum(F105:F134) -> -1389.1 | G6: =sum(G105:G134) -> -548.66 | H6: =sum(H105:H134) -> 0 | I6: =sum(I105:I134) -> 0 | J6: =sum(J105:J134) -> -141.55 | K6: =sum(K105:K134) -> -29.75
A7: May | B7: =sum(E135:K165) -> -4347.43 | C7: ='2020_income'!B7 -> 4718.97 | D7: =SUM(B7,C7) -> 371.54 | E7: =sum(E135:E165) -> -160.58 | F7: =sum(F135:F165) -> -939.2 | G7: =sum(G135:G165) -> -35 | H7: =sum(H135:H165) -> -175 | I7: =sum(I135:I165) -> 0 | J7: =sum(J135:J165) -> -501.43 | K7: =sum(K135:K165) -> -2536.22
A8: Jun | B8: =sum(E166:K195) -> -2016.81 | C8: ='2020_income'!B8 -> 6233.97 | D8: =SUM(B8,C8) -> 4217.16 | E8: =sum(E166:E195) -> -129.27 | F8: =sum(F166:F195) -> -1260.15 | G8: =sum(G166:G195) -> -40.95 | H8: =sum(H166:H195) -> -414 | I8: =sum(I166:I195) -> 0 | J8: =sum(J166:J195) -> -72 | K8: =sum(K166:K195) -> -100.44
A9: Jul | B9: =sum(E196:K226) -> -4377.55 | C9: ='2020_income'!B9 -> 14377.38 | D9: =SUM(B9,C9) -> 9999.83 | E9: =sum(E196:E226) -> -188.27 | F9: =sum(F196:F226) -> -3439.04 | G9: =sum(G196:G226) -> -666.9 | H9: =sum(H196:H226) -> -20.51 | I9: =sum(I196:I226) -> 0 | J9: =sum(J196:J226) -> 0 | K9: =sum(K196:K226) -> -62.83
A10: Aug | B10: =sum(E227:K257) -> -8208.13 | C10: ='2020_income'!B10 -> 4898.3 | D10: =SUM(B10,C10) -> -3309.83 | E10: =sum(E227:E257) -> -5.59 | F10: =sum(F227:F257) -> -1863.64 | G10: =sum(G227:G257) -> -1270 | H10: =sum(H227:H257) -> 0 | I10: =sum(I227:I257) -> -4875.4 | J10: =sum(J227:J257) -> -86.68 | K10: =sum(K227:K257) -> -106.82
A11: Sep | B11: =sum(E258:K287) -> -4292.02 | C11: ='2020_income'!B11 -> 7877.6 | D11: =SUM(B11,C11) -> 3585.58 | E11: =sum(E258:E287) -> -97.79 | F11: =sum(F258:F287) -> -1584.54 | G11: =sum(G258:G287) -> -1972.5 | H11: =sum(H258:H287) -> 0 | I11: =sum(I258:I287) -> 0 | J11: =sum(J258:J287) -> -82 | K11: =sum(K258:K287) -> -555.19
A12: Oct | B12: =sum(E288:K318) -> -2926.93 | C12: ='2020_income'!B12 -> 2847.19 | D12: =SUM(B12,C12) -> -79.74 | E12: =sum(E288:E318) -> -39.14 | F12: =sum(F288:F318) -> -1182.75 | G12: =sum(G288:G318) -> -1428.28 | H12: =sum(H288:H318) -> 0 | I12: =sum(I288:I318) -> 0 | J12: =sum(J288:J318) -> -69.47 | K12: =sum(K288:K318) -> -207.29
A13: Nov | B13: =sum(E319:K348) -> -7533.37 | C13: ='2020_income'!B13 -> 4917.39 | D13: =SUM(B13,C13) -> -2615.98 | E13: =sum(E319:E348) -> -203.62 | F13: =sum(F319:F348) -> -1565.78 | G13: =sum(G319:G348) -> -2014.1 | H13: =sum(H319:H348) -> -687.29 | I13: =sum(I319:I348) -> 0 | J13: =sum(J319:J348) -> -1059.02 | K13: =sum(K319:K348) -> -2003.56
A14: Dec | B14: =sum(E349:K379) -> -4424.19 | C14: ='2020_income'!B14 -> 5869.94 | D14: =SUM(B14,C14) -> 1445.75 | E14: =sum(E349:E379) -> -217.34 | F14: =sum(F349:F379) -> -1535.65 | G14: =sum(G349:G379) -> -1748.73 | H14: =sum(H349:H379) -> 0 | I14: =sum(I349:I379) -> -44.49 | J14: =sum(J349:J379) -> -368.31 | K14: =sum(K349:K379) -> -509.67
A15: 43831
A16: 43832 | F16: =-sum(4.25,10,1.4,68,1,23.5,5,12.15,12.72,35.95) -> -173.97
A17: 43833
A18: 43834 | E18: -10 | F18: -7.5
A19: 43835 | E19: =-sum(7.5,13.32) -> -20.82 | F19: =sum(-153.62,27.42,41.3) -> -84.9
A20: 43836 | E20: -47.27 | F20: =-sum(11.4,8) -> -19.4
A21: 43837 | E21: -5 | F21: =-sum(8.6,23.4,35.93,9) -> -76.93
A22: 43838 | E22: -37.48
A23: 43839 | E23: -5.83 | F23: -55 | G23: -175.59
A24: 43840 | E24: =-sum(43.51,1.4,32) -> -76.91 | F24: =-sum(20.5,37.8) -> -58.3 | G24: -75.53
A25: 43841 | E25: -47.31 | F25: =-sum(45.25,4,2.3) -> -51.55
A26: 43842 | F26: =-sum(10.69,4.99) -> -15.68
A27: 43843 | F27: =-sum(63.99,16.5,19.5,24.85) -> -124.84
A28: 43844 | F28: =-sum(36.08,3,31.5,2.2,42.86) -> -115.64
A29: 43845 | F29: =-sum(30.2,21.29) -> -51.49
A30: 43846 | F30: =-sum(11.3,17.98,27.43,37.45) -> -94.16
A31: 43847 | F31: =-sum(43.11,20.95,29.8) -> -93.86
A32: 43848 | F32: =-sum(21.89,2.8,20) -> -44.69
A33: 43849
A34: 43850 | F34: =-sum(7,2.99,2.8,13.45) -> -26.24 | J34: -101.96
A35: 43851 | F35: =-sum(5.45,7.5,21.45) -> -34.4
A36: 43852 | F36: =-sum(16.9,4.2) -> -21.1
A37: 43853 | F37: =-sum(6,7.5,29.5) -> -43
A38: 43854 | F38: -30
A39: 43855 | E39: -39.3 | F39: =-sum(9.1,22.47,48.2,3.75,2.8,6.37) -> -92.69
A40: 43856 | E40: -20
A41: 43857 | F41: -21
A42: 43858 | F42: =-sum(18.91,3,2,42.89,23.3,166.5,24.1) -> -280.7
A43: 43859 | F43: =-sum(8,4.65) -> -12.65
A44: 43860
A45: 43861 | E45: -32.39
A46: 43862 | F46: =-sum(2.8,6,5.6,4.72,4.99) -> -24.11
A47: 43863 | F47: -25.35
A48: 43864 | F48: -76.7
A49: 43865 | E49: -23.92 | F49: =-sum(72.48,3.7) -> -76.18
A50: 43866 | F50: -19.2
A51: 43867 | F51: =-sum(5.6,3) -> -8.6 | G51: -215.92
A52: 43868 | F52: -8.84
A53: 43869 | F53: =-sum(19.95,15.68,2) -> -37.63
A54: 43870 | F54: =-sum(19.2,12.94,32.36) -> -64.5
A55: 43871 | F55: =-sum(25.63,19,42.23) -> -86.86
A56: 43872 | F56: -430
A57: 43873 | F57: =-sum(11.1,2.7) -> -13.8
A58: 43874 | E58: =-sum(3.04,33.37) -> -36.41 | F58: =-sum(3,20,4.2) -> -27.2
A59: 43875 | F59: =-sum(8.4,33.5,2.41,2.8) -> -47.11
A60: 43876 | F60: =-sum(5.6,10.98,17.05) -> -33.63
A61: 43877 | F61: =-sum(15,19.11,5.6,15.98,11.9,19.57,14.97) -> -102.13
A62: 43878 | F62: =-sum(18.1,7.65,11.22) -> -36.97
A63: 43879 | E63: -5 | F63: -3
A64: 43880 | F64: =-sum(29,3) -> -32
A65: 43881 | F65: =-sum(5.8,11.9,40.63) -> -58.33
A66: 43882 | F66: =-sum(55.7,33.6) -> -89.3
A67: 43883 | F67: =-sum(10,5.5,5.6,-50) -> 28.9
A68: 43884 | E68: -30.47 | F68: =-sum(18.1,30,10.35) -> -58.45 | G68: -66.31
A69: 43885 | F69: =-sum(10.3,6.9,8.8,21,4.38,21.58) -> -72.96
A70: 43886 | F70: =-sum(173.4,8.4,6.3,5.8) -> -193.9 | J70: -16.5 | K70: 42.86
A71: 43887 | F71: =-sum(61.35,13.75,6.4,2.8,8) -> -92.3
A72: 43888 | F72: =-sum(13.75,99.32) -> -113.07
A73: 43889 | E73: =-sum(34.5,20) -> -54.5 | F73: =-sum(18.4,11) -> -29.4
A74: 43890 | F74: -19.37
A75: 43891 | F75: =-sum(3.4,9) -> -12.4 | J75: -78.01
A76: 43892 | E76: -31.55 | F76: =-sum(2.9,12.04,5.6,24.17,21.1) -> -65.81
A77: 43893 | F77: =-sum(32,99.4) -> -131.4
A78: 43894 | F78: -18.86
A79: 43895 | F79: -18 | G79: -35
A80: 43896 | E80: -36.93 | F80: -28.5
A81: 43897 | F81: =-sum(10,21,2.5,5.6,2.9,13.99,29.52) -> -85.51
A82: 43898 | F82: =-sum(3.5,22.78) -> -26.28
A83: 43899 | F83: =-sum(25.25,13.07,10.26) -> -48.58
A84: 43900 | F84: =-sum(9.9,2.5,20.2) -> -32.6
A85: 43901 | E85: -32.53 | F85: -3.2
A86: 43902 | E86: -20 | F86: =-sum(6.9,5.5,15.1) -> -27.5
A87: 43903 | F87: =-sum(2.8,5.5,36.5) -> -44.8
A88: 43904 | F88: =-sum(4,6.62,13.5) -> -24.12
A89: 43905 | F89: =-sum(49.28,27.02,11.8,19.48,5.5,14.72) -> -127.8
A90: 43906 | F90: =-sum(35,49.1,7,15.9) -> -107
A91: 43907 | F91: =-sum(6,19.35) -> -25.35
A92: 43908 | F92: =-sum(15,15.3) -> -30.3
A93: 43909 | E93: -32.93 | G93: -716.87 | J93: -37.98
A94: 43910 | F94: -20.5
A95: 43911 | E95: -10.15 | F95: =-sum(18.63) -> -18.63
A96: 43912 | E96: -33.88 | F96: -44.2
A97: 43913 | F97: =-sum(58.85,44.15,45.87,5.49) -> -154.36
A98: 43914 | F98: =-sum(7.7,112.63) -> -120.33
A99: 43915 | F99: -91.7 | I99: -4914.08
A100: 43916
...

Sheet 2020_income
B1: INCOME | C1: interest | D1: Will | E1: Yan | F1: Salary Package | H1: Monthly balance
B2: =sum(C2:F2) -> 76938.88 | C2: =sum(C3:C1000) -> 3780.49 | D2: =sum(D3:D1000) -> 25139.03 | E2: =sum(E3:E1000) -> 36654.47 | F2: =sum(F3:F1000) -> 11364.89 | H2: =SUM(H3:H1000) -> 76938.88
A3: JAN | B3: =SUM(C3:F3) -> 5800 | C3: =sum(468.82,25.2) -> 494.02 | D3: =sum(747.29,456.21) -> 1203.5 | E3: =SUM(1645.22,1119.7) -> 2764.92 | F3: =sum(668.78*2) -> 1337.56 | H3: =SUM(B3,'2020'!M15) -> 5800
A4: Feb | B4: =SUM(C4:F4) -> 6670.56 | C4: =sum(494.82,26.6) -> 521.42 | D4: =sum(1171.42,1110.19) -> 2281.61 | E4: =sum(1440.13,1089.84) -> 2529.97 | F4: =668.78*2 -> 1337.56 | H4: =SUM(B4,'2020'!M16) -> 6670.56
A5: MAR | B5: =SUM(C5:F5) -> 6975.52 | C5: =sum(176.3,119.97) -> 296.27 | D5: =sum(825.37,708.84) -> 1534.21 | E5: =sum(1357.9,1424.18,1349.48) -> 4131.56 | F5: =sum(668.78,344.7) -> 1013.48 | H5: =SUM(B5,'2020'!M17) -> 6975.52
A6: APR | B6: =SUM(C6:F6) -> 5752.06 | C6: 396.82 | D6: 750 | E6: =sum(2147.25,1768.59) -> 3915.84 | F6: =344.7*2 -> 689.4 | H6: =SUM(B6,'2020'!M18) -> 5752.06
A7: MAY | B7: =SUM(C7:F7) -> 4718.97 | C7: 336.15 | D7: 1000 | E7: =sum(1310.08,1405.34) -> 2715.42 | F7: =333.7*2 -> 667.4 | H7: =SUM(B7,'2020'!M19) -> 4718.97
A8: JUN | B8: =SUM(C8:F8) -> 6233.97 | C8: 279.99 | D8: =sum(1345.08,726.53) -> 2071.61 | E8: =sum(1655.61,1542.74) -> 3198.35 | F8: =sum(333.7,350.32) -> 684.02 | H8: =SUM(B8,'2020'!M20) -> 6233.97
A9: JUL | B9: =SUM(C9:F9) -> 14377.38 | C9: 288.45 | D9: =sum(567.28,1147.84,702,177.88,797.22) -> 3392.22 | E9: =sum(1238.62,7678.6,1078.85) -> 9996.07 | F9: =sum(350.32*2) -> 700.64 | H9: =SUM(B9,'2020'!M21) -> 14377.38 | I9: =H9-702-7678.6 -> 5996.78
A10: AUG | B10: =SUM(C10:F10) -> 4898.3 | C10: 267.97 | D10: =sum(877.98,729.25) -> 1607.23 | E10: =sum(1117.37,1205.09) -> 2322.46 | F10: =350.32*2 -> 700.64 | H10: =SUM(B10,'2020'!M22) -> 4898.3
A11: SEP | B11: =SUM(C11:F11) -> 7877.6 | C11: 268.19 | D11: =sum(51.23,27.08,10.88,1429,5,189.56,76.16,184.78,1432.8) -> 3406.49 | E11: =sum(1294.79,50,1202.67,363.91) -> 2911.37 | F11: =350.32+450.79+490.44 -> 1291.55 | H11: =SUM(B11,'2020'!M23) -> 7877.6
A12: OCT | B12: =SUM(C12:F12) -> 2847.19 | C12: 225.99 | D12: =sum(189.42,74.76)*2+434.14 -> 962.5 | E12: =sum(313.91,363.91) -> 677.82 | F12: =sum(490.44)*2 -> 980.88 | H12: =SUM(B12,'2020'!M24) -> 2847.19
A13: NOV | B13: =SUM(C13:F13) -> 4917.39 | C13: 208.83 | D13: =sum(765.6,189.42,74.76,762.47,189.42,74,940.19) -> 2995.86 | E13: =365.91*2 -> 731.82 | F13: =490.44*2 -> 980.88 | H13: =SUM(B13,'2020'!M25) -> 4917.39
A14: DEC | B14: =SUM(C14:F14) -> 5869.94 | C14: 196.39 | D14: =sum(334, 189.42,74.76,998.48,543.54,189.42,74.76,883.91,381.33,189.42,74.76) -> 3933.8 | E14: =365.91+392.96 -> 758.87 | F14: =sum(490.44*2) -> 980.88 | H14: =SUM(B14,'2020'!M26) -> 5869.94

Sheet 2019_1
B1: Expense | C1: income | D1: Net Profit | E1: Transport | F1: Living | G1: Bill | H1: License | I1: RMIT | J1: Autumn | K1: Others | L1: Monthly expected | Q1: HKD | R1: HKD | S1: HKD
B2: =SUM(E2:K2) -> -36496.54 | C2: =SUM(C16:C1011, '2019_2'!B1:B1011) -> 55001.27 | D2: =SUM(B2,C2) -> 18504.73 | E2: =SUM(E16:E1011) -> -2139.41 | F2: =SUM(F17:F1011) -> -10619.79 | G2: =SUM(G16:G1011) -> -1749.65 | H2: =SUM(H17:H1011) -> -651.66 | I2: =SUM(I17:I1011) -> -8475.39 | J2: =SUM(J17:J1011) -> -850.75 | K2: =SUM(K17:K1011) -> -12009.89 | Q2: =sum((B2)*5.6) -> -204380.62 | R2: =sum((C2)*5.6) -> 308007.11 | S2: =sum((D2)*5.6) -> 103626.49
A16: 43516 | C16: 9865 | E16: -5 | F16: =-sum(13.5,26.2) -> -39.7
A17: 43517 | E17: -10 | F17: =-sum(8.85,10,32.5) -> -51.35 | H17: -18.5 | N17: convert license
N18: myki
N19: cooking stuff
A20: 43518 | N20: dinner
A21: 43519 | N21: lunch
E22: -6 | N22: parking
F23: -4 | N23: dinner
F24: -17.6 | N24: rice
A25: 43520 | F25: -7 | N25: veggieball
F26: -9.75 | N26: dinner
A27: 43521 | F27: -27.3 | N27: dinner
A28: 43524 | K28: -9300 | N28: CAR
A29: 43525 | C29: 11800 | N29: saving
E30: -30.8 | N30: myki
F31: -5.3 | N31: dinner
F32: -7.35 | N32: dinner
A33: 43527 | F33: -5.6 | N33: lunch
E34: -55.95 | N34: fuel
F35: -10.56 | N35: dinner
A36: 43528 | F36: -9 | N36: lunch
F37: -8.95 | N37: dinner
A38: 43529 | F38: -12.3 | N38: lunch
I39: -3620.76 | N39: sem 1 fee
A40: 43530 | F40: -41.8 | N40: dinner
A41: 43531 | E41: -20 | N41: myki
I42: -26.95 | N42: lab coat skin pencil
F43: -9.8
F44: -11.15
A45: 43537 | H45: -278.16 | N45: license
A46: 43539 | F46: -9.9 | N46: lunch
E47: -41 | N47: fuel
F48: -61 | N48: lunch
E49: -12 | N49: parking
E50: -13
E51: -12
F52: -19.1 | N52: food
C53: 234
E54: -3.76 | N54: school parking
E55: -4.4
E56: -2.3
A57: 43543 | F57: -12.5 | N57: lunch
H58: -123.4 | N58: WCCC
A59: 43545 | F59: -31 | N59: food
E60: -51 | N60: fuel
F61: -11 | N61: lunch
F62: -9.9 | N62: lunch
F63: -2.7 | N63: 煉奶
F64: -30 | N64: prepaid
F65: -22 | N65: food
E66: -5 | N66: parking
A67: 43550 | F67: -9.5 | N67: lunch
F68: -9.5 | N68: ear wash
F69: -17.75 | N69: food
E70: -$5 | N70: school park
A71: 43551
A72: 43552 | F72: -39.8
A73: 43553 | F73: -43
A74: 43554
A75: 43555
A76: 43556 | F76: =sum(-9.5,-17.2) -> -26.7 | K76: -129
A77: 43557 | F77: -9
A78: 43558 | F78: -21
A79: 43559 | F79: -10
A80: 43560 | F80: -30.5
A81: 43561
A82: 43562
A83: 43563 | E83: -10 | F83: -30.7
A84: 43564 | E84: -66.9 | F84: -11.5
A85: 43565
A86: 43566 | E86: -2.3 | F86: -56.63
A87: 43567 | F87: -77.17
A88: 43568 | E88: -3.5 | F88: -9.9 | K88: -20
A89: 43569 | F89: -4.25 | K89: -33
A90: 43570 | F90: -43
A91: 43571 | E91: -4.5 | F91: -25 | K91: -19.84
A92: 43572 | F92: -23.4
A93: 43573
A94: 43574 | F94: -10
A95: 43575 | F95: -15.32
A96: 43576
A97: 43577
A98: 43578 | F98: -31.55
A99: 43579 | F99: -36.9
A100: 43580
A101: 43581 | F101: -46.52
A102: 43582 | E102: -10 | F102: -13.5
A103: 43583
A104: 43584 | F104: -24
A105: 43585 | F105: -28.8
A106: 43586 | F106: -9
A107: 43587 | F107: -34
A108: 43588
A109: 43589
A110: 43590 | E110: -50 | F110: -25
A111: 43591 | F111: -15.5
A112: 43592 | F112: -100
A113: 43593 | F113: -11.2
...

Sheet 2019_2
A1: Income | D1: Saving | E1: =sum(E2:E1003) -> 33336.27
A2: April interest | B2: =sum(42.63,-19) -> 23.63 | D2: MAY | E2: =SUM(B2:B5,'2019_1'!M16,234) -> 399.46
A3: 43578 | B3: 25.13 | C3: RMIT
A4: May interest | B4: 41.31
A5: 43593 | B5: 75.39 | C5: RMIT
A6: 43621 | B6: 50.28 | C6: RMIT
A7: June interest | B7: 75.79 | D7: JUNE | E7: =sum(B6:B11,'2019_1'!M17) -> 2180.07
A8: 1st week of June | B8: 500.5 | C8: 糖樓
A9: 2nd week of June | B9: 455 | C9: 糖樓
A10: 3rd June | B10: 539.5 | C10: 糖樓
A11: 4th June | B11: 559 | C11: 糖樓
A12: July interest | B12: 174.42 | D12: JULY | E12: =sum(B12:B17,'2019_1'!M18) -> 3153.86
A13: 1st week of July | B13: 443.6 | C13: 糖樓
A14: 2nd July | B14: 559 | C14: 糖樓
A15: 3rd July | B15: 546 | C15: 糖樓
A16: 3rd July | B16: 1053.84 | C16: RCH
A17: 4th July | B17: 377 | C17: 糖樓
A18: August Interest | B18: 197.54 | D18: AUGUST | E18: =sum(B18:B24,'2019_1'!M19) -> 5596
A19: 1 st week of Aug | B19: 1574.94 | C19: RCH
A20: 1 st week of Aug | B20: 367.25 | C20: 糖樓
A21: 2nd week of Aug | B21: 370.5 | C21: 糖樓
B22: 364 | C22: 糖樓
B23: 2357.77 | C23: RCH
B24: 364
A25: Sept | B25: 487 | D25: Sept | E25: =sum(B25:B28,'2019_1'!M20) -> 3329.51
A26: Sept | B26: 1517.08
B27: 17.95
B28: 1307.48
A29: Oct | B29: 161.33 | C29: interest | D29: Oct | E29: =sum(B29:B36,'2019_1'!M21) -> 5743.62
B30: 1099.75
B31: 800.78 | C31: salary package
B32: 1119.7
B33: 643.56 | C33: salary package
B34: 55 | C34: ATO
B35: 1219.94
B36: 643.56
A37: Nov | B37: 373.68 | C37: interest | D37: Nov | E37: =sum(B37:B43,'2019_1'!M22) -> 6299.52
B38: 1075.34 | C38: Daiso
B39: 668.78 | C39: SalaryPackage
B40: 1300.48 | C40: RCH
B41: 1079.92 | C41: Daiso
B42: 668.78 | C42: Salary Pack
B43: 1132.54 | C43: RCH
A44: Dec | B44: =SUM(356.93,19.18) -> 376.11 | C44: interest | D44: Dec | E44: =sum(B44:B51,'2019_1'!M23) -> 6634.23
B45: 429.45 | C45: Daiso
B46: 1214.59 | C46: RCH
B47: 668.78 | C47: SS
B48: 841.19 | C48: Daiso
B49: 1320.18 | C49: RCH | G49: =sum(B37,B44,B29,B18,B12) -> 1283.08
B50: 668.78 | C50: SS
B51: 1115.15 | C51: Daiso

Sheet Total_earning
A1: YEAR | B1: MONTH | C1: Expense | D1: income | E1: Net Profit | F1: Transport | G1: Living | H1: Bill | I1: Groceries | J1: Dine | K1: RMIT | L1: Mortgage | M1: Childcare | N1: Will | O1: Yan | P1: Salary Package | Q1: Interest
A2: 2020 | B2: 1 | C2: -2325.08 | D2: 5800 | E2: 3474.92 | F2: -342.31 | G2: -1731.65 | H2: -251.12 | J2: 0 | K2: 0 | L2: 0 | M2: 0 | N2: 1697.52 | O2: =SUM(1645.22,1119.7) -> 2764.92 | P2: =sum(668.78*2) -> 1337.56
A3: 2020 | B3: 2 | C3: -2238.79 | D3: 6670.56 | E3: 4431.77 | F3: -150.3 | G3: -1806.26 | H3: -282.23 | J3: 0 | K3: 0 | L3: 0 | M3: 0 | N3: 2803.03 | O3: =sum(1440.13,1089.84) -> 2529.97 | P3: =668.78*2 -> 1337.56
A4: 2020 | B4: 3 | C4: -7341.57 | D4: 6975.52 | E4: -366.05 | F4: -197.97 | G4: -1477.65 | H4: -751.87 | J4: 0 | K4: -4914.08 | L4: 0 | M4: 0 | N4: 1830.48 | O4: =sum(1357.9,1424.18,1349.48) -> 4131.56 | P4: =sum(668.78,344.7) -> 1013.48
A5: 2020 | B5: 4 | C5: -2233.24 | D5: 5752.06 | E5: 3518.82 | F5: -124.18 | G5: -1560.4 | H5: -548.66 | J5: 0 | K5: 0 | L5: 0 | M5: 0 | N5: 1146.82 | O5: =sum(2147.25,1768.59) -> 3915.84 | P5: =344.7*2 -> 689.4
A6: 2020 | B6: 5 | C6: -4347.43 | D6: 4718.97 | E6: 371.54 | F6: -160.58 | G6: -3976.85 | H6: -35 | J6: -175 | K6: 0 | L6: 0 | M6: 0 | N6: 1336.15 | O6: =sum(1310.08,1405.34) -> 2715.42 | P6: =333.7*2 -> 667.4
A7: 2020 | B7: 6 | C7: -2016.81 | D7: 6233.97 | E7: 4217.16 | F7: -129.27 | G7: -1432.59 | H7: -40.95 | J7: -414 | K7: 0 | L7: 0 | M7: 0 | N7: 2351.6 | O7: =sum(1655.61,1542.74) -> 3198.35 | P7: =sum(333.7,350.32) -> 684.02
A8: 2020 | B8: 7 | C8: -4377.55 | D8: 14377.38 | E8: 9999.83 | F8: -188.27 | G8: -3501.87 | H8: -666.9 | J8: -20.51 | K8: 0 | L8: 0 | M8: 0 | N8: 3680.67 | O8: =sum(1238.62,7678.6,1078.85) -> 9996.07 | P8: =sum(350.32*2) -> 700.64
A9: 2020 | B9: 8 | C9: -8208.13 | D9: 4898.3 | E9: -3309.83 | F9: -5.59 | G9: -2057.14 | H9: -1270 | J9: 0 | K9: -4875.4 | L9: 0 | M9: 0 | N9: 1875.2 | O9: =sum(1117.37,1205.09) -> 2322.46 | P9: =350.32*2 -> 700.64
A10: 2020 | B10: 9 | C10: -4292.02 | D10: 7877.6 | E10: 3585.58 | F10: -97.79 | G10: -2221.73 | H10: -1972.5 | J10: 0 | K10: 0 | L10: 0 | M10: 0 | N10: 3674.68 | O10: =sum(1294.79,50,1202.67,363.91) -> 2911.37 | P10: =350.32+450.79+490.44 -> 1291.55
A11: 2020 | B11: 10 | C11: -2926.93 | D11: 2847.19 | E11: -79.74 | F11: -39.14 | G11: -1459.51 | H11: -1428.28 | J11: 0 | K11: 0 | L11: 0 | M11: 0 | N11: 1188.49 | O11: =sum(313.91,363.91) -> 677.82 | P11: =sum(490.44)*2 -> 980.88
A12: 2020 | B12: 11 | C12: -7533.37 | D12: 4917.39 | E12: -2615.98 | F12: -203.62 | G12: -4628.36 | H12: -2014.1 | J12: -687.29 | K12: 0 | L12: 0 | M12: 0 | N12: 3204.69 | O12: =365.91*2 -> 731.82 | P12: =490.44*2 -> 980.88
A13: 2020 | B13: 12 | C13: -4424.19 | D13: 5869.94 | E13: 1445.75 | F13: -217.34 | G13: -2413.63 | H13: -1748.73 | J13: 0 | K13: -44.49 | L13: 0 | M13: 0 | N13: 4130.19 | O13: =365.91+392.96 -> 758.87 | P13: =sum(490.44*2) -> 980.88
A14: 2021 | B14: 1 | C14: -4546.05 | D14: 4787.32 | E14: 241.27 | F14: -1159.4 | G14: -1594.28 | H14: -1792.37 | J14: 0 | K14: 0 | L14: 0 | M14: 0 | N14: =sum(1160.56,177.57,1455.24,87.22) -> 2880.59 | O14: =sum(388.96*2) -> 777.92 | P14: =490.44*2 -> 980.88
A15: 2021 | B15: 2 | C15: -4022.84 | D15: 5244.63 | E15: 1221.79 | F15: -396.44 | G15: -1531.4 | H15: -1270 | J15: 0 | K15: -825 | L15: 0 | M15: 0 | N15: =sum(1248.97,82.36,842.45,79.52) -> 2253.3 | O15: =sum(767.4,2094.6) -> 2862 | P15: 0
A16: 2021 | B16: 3 | C16: -9522.24 | D16: 6870.83 | E16: -2651.41 | F16: -236.24 | G16: -1969.64 | H16: -2768.4 | J16: 0 | K16: -4547.96 | L16: 0 | M16: 0 | N16: =sum(1305.57,250,79.66,879.46,79.66,843.82) -> 3438.17 | O16: =sum(1111.8,1111.8,1111.8) -> 3335.4 | P16: 0
A17: 2021 | B17: 4 | C17: -3484.77 | D17: 4899.62 | E17: 1414.85 | F17: -253.32 | G17: -1927.95 | H17: -1303.5 | J17: 0 | K17: 0 | L17: 0 | M17: 0 | N17: =sum(79.66,1103.72,15.07,79.66,993.5) -> 2271.61 | O17: =sum(1111.8,261.75,1111.8,28) -> 2513.35 | P17: 0
A18: 2021 | B18: 5 | C18: -4418.27 | D18: 5290.61 | E18: 872.34 | F18: -182.92 | G18: -1964.48 | H18: -2080 | J18: -190.87 | K18: 0 | L18: 0 | M18: 0 | N18: =sum(113.96,1189.68,175.7,1224.99) -> 2704.33 | O18: =sum(1111.8,200,50,1111.8,20.39) -> 2493.99 | P18: 0
A19: 2021 | B19: 6 | C19: -4732.87 | D19: 2717.1 | E19: -2015.77 | F19: -99.38 | G19: -1780.15 | H19: -1347.2 | J19: 0 | K19: -1506.14 | L19: 0 | M19: 0 | N19: =sum(175.7,848.77,147.64,189.56,11.92,865.9,174.02,189.56) -> 2603.07 | O19: 0 | P19: 0
A20: 2021 | B20: 7 | C20: -9434.34 | D20: 9980.34 | E20: 546 | F20: -227.07 | G20: -1970.99 | H20: -3162.34 | J20: 0 | K20: -4073.94 | L20: 0 | M20: 0 | N20: =sum(242.4,982.62,292.05,645.2,450,353.78) -> 2966.05 | O20: =sum(500,6471.04) -> 6971.04 | P20: 0
A21: 2021 | B21: 8 | C21: -9442.08 | D21: 8090.33 | E21: -1351.75 | F21: -279.96 | G21: -2127.21 | H21: =sum(-2487.87,1883) -> -604.87 | J21: 0 | K21: -4547.04 | L21: -1883 | M21: 0 | N21: =sum(600,660.18,375,94.69,350,750,861.1,40,750,74.76,750) -> 5305.73 | O21: =sum(888.8,20,1312.75) -> 2221.55 | P21: 563.05
A22: 2021 | B22: 9 | C22: -6645.2 | D22: 10360.59 | E22: 3715.39 | F22: -219.48 | G22: -1903.98 | H22: =sum(-2522.74,1883) -> -639.74 | J22: 0 | K22: -1999 | L22: -1883 | M22: 0 | N22: =sum(669.77,750,74.76,750,129.94,47.18,450,750,74.76,750,871.2,750,74.76) -> 6142.37 | O22: =sum(200,1353.09,1539.03) -> 3092.12 | P22: =sum(563.05,563.05) -> 1126.1
A23: 2021 | B23: 10 | C23: -7835.09 | D23: 9938.69 | E23: 2103.6 | F23: -1248.28 | G23: -2911.03 | H23: =sum(-3592.48,1883) -> -1709.48 | J23: 0 | K23: -83.3 | L23: -1883 | M23: 0 | N23: =sum(750,873.99,750,750,74.76,1031.1,750) -> 4979.85 | O23: =sum(20.15,1410.55,40.59,1.5,55,1186.95) -> 2714.74 | P23: =sum(563.05,1118,563.05) -> 2244.1
A24: 2021 | B24: 11 | C24: -6716.28 | D24: 12165.04 | E24: 5448.76 | F24: -393.05 | G24: -2927.56 | H24: =sum(-2549.77,1883) -> -666.77 | J24: -845.9 | K24: 0 | L24: -1883 | M24: 0 | N24: =sum(74.76,450,750,450,527.4,516.63,74.76,320,971.55) -> 4135.1 | O24: =sum(1,450,450,1548.19,450,1.5,320,1284.95,104.5) -> 4610.14 | P24: =sum(998.4,563.05,1190.8,563.05,104.5) -> 3419.8
A25: 2021 | B25: 12 | C25: -2944.91 | D25: 6155.67 | E25: 3210.76 | F25: ='2021'!E14 -> -423.51 | G25: ='2021'!F14 -> -2396.11 | H25: ='2021'!G14+1883 -> -865.56 | J25: 0 | K25: 0 | L25: -1883 | M25: 0 | N25: ='2021_income'!D14 -> 6174.99 | O25: ='2021_income'!E14 -> 3181.89 | P25: ='2021_income'!F14 -> 1983.05
A26: 2022 | B26: 1 | C26: -5045.13 | D26: 10557.88 | E26: 5512.75 | F26: -338.45 | G26: -813.08 | H26: -201.19 | I26: -1230.37 | J26: -350.93 | K26: 0 | L26: -1883 | M26: -228.11 | N26: =sum(923.16,1131.25*2,74.76*2,974.35,50.98,450,15.03) -> 4825.54 | O26: =sum(2010.14,25,1663.2,450,0.52,28.72) -> 4177.58 | P26: =sum(56.09,506.96,563.24,428.47) -> 1554.76
A27: 2022 | B27: 2 | C27: -4644.96 | D27: 8373.77 | E27: 3728.81 | F27: -384.43 | G27: -434.69 | H27: -385.33 | I27: -988.27 | J27: -365.68 | K27: 0 | L27: -1883 | M27: -203.56 | N27: =sum(302.71,1131.25*2,74.76*2,644.63) -> 3359.36 | O27: =sum(1398.72,1646.21,1.04) -> 3045.97 | P27: =sum(563.24,563.24,841.96) -> 1968.44
A28: 2022 | B28: 3 | C28: -7774.84 | D28: 11850.93 | E28: 4076.09 | F28: -414.24 | G28: -1665.07 | H28: -1864.71 | I28: -1151.24 | J28: -507.76 | K28: 0 | L28: -1889 | M28: -282.82 | N28: =sum(903.86,1131.25,74.76,753.87,1122.25,74.76) -> 4060.75 | O28: =sum(1499.71,0.52,31.12,609.94,1724.2,1625.03) -> 5490.52 | P28: =sum(563.24,609.94,56.09,507.15,563.24) -> 2299.66
A29: 2022 | B29: 4 | C29: -5793.35 | D29: 9846.13 | E29: 4052.78 | F29: -112.65 | G29: -1657.91 | H29: -439.93 | I29: -696.43 | J29: -786.23 | K29: 0 | L29: -1889 | M29: -211.2 | N29: =sum(2632.08*2,74.76*2) -> 5413.68 | O29: =sum(1559.42,2179.97) -> 3739.39 | P29: =sum(346.53,56.09,290.44) -> 693.06
A30: 2022 | B30: 5 | C30: -4398.68 | D30: 9554.11 | E30: 5155.43 | F30: -20 | G30: -442.93 | H30: -864.25 | I30: -452.94 | J30: -518.36 | K30: 0 | L30: -1889 | M30: -211.2 | N30: =sum(2632.08*2,74.76*2) -> 5413.68 | O30: =sum(54.5,18.95,1645.01,1728.91) -> 3447.37 | P30: =sum(346.53,346.53) -> 693.06
A31: 2022 | B31: 6 | C31: -9688.97 | D31: 12136.95 | E31: 2447.98 | F31: -78.75 | G31: -6685.75 | H31: -343.97 | I31: -418.28 | J31: -62.02 | K31: 0 | L31: -1889 | M31: -211.2 | N31: =sum(2632.08,74.76*3,2677.26*2) -> 8210.88 | O31: =sum(1543.92,1689.09) -> 3233.01 | P31: =sum(346.53,346.53) -> 693.06
A32: 2022 | B32: 7 | C32: -12560.03 | D32: 18385.52 | E32: 5825.49 | F32: -67.6 | G32: -1156.13 | H32: -3675.52 | I32: -593.64 | J32: -281.94 | K32: -14545 | L32: -1889 | M32: -351.2 | N32: =sum(2677.26*2,10.68) -> 5365.2 | O32: =sum(1931.09,1540.69,8855.48) -> 12327.26 | P32: =sum(346.53,346.53) -> 693.06
A33: 2022 | B33: 8 | C33: -11976.91 | D33: 12238.99 | E33: 262.08 | F33: -62.64 | G33: -4501.84 | H33: -3723.01 | I33: -987.84 | J33: -367.14 | K33: 0 | L33: -1889 | M33: -445.44 | N33: =sum(2677.26*2) -> 5354.52 | O33: =sum(1814.29,1451.42,2366.46) -> 5632.17 | P33: =sum(346.53,346.53,145.62,67.09,346.53) -> 1252.3
A34: 2022 | B34: 9 | C34: -6346.19 | D34: 9561.5 | E34: 3215.31 | F34: -10 | G34: -1581.72 | H34: -673.74 | I34: -935.85 | J34: -570.97 | K34: 0 | L34: -1935 | M34: -638.91 | N34: =sum(2677.26)*2 -> 5354.52 | O34: =sum(1463.94,1749.78) -> 3213.72 | P34: =sum(154.57,342.06,342.06,154.57) -> 993.26
A35: 2022 | B35: 10 | C35: -5861.75 | D35: 10052.65 | E35: 4190.9 | F35: -81.3 | G35: -1369.52 | H35: -905.01 | I35: -569.33 | J35: -497.18 | K35: 0 | L35: -1935 | M35: -504.41 | N35: =sum(2677.26)*2 -> 5354.52 | O35: =sum(2337.59,1367.28) -> 3704.87 | P35: =sum(342.06*2,154.57*2) -> 993.26
A36: 2022 | B36: 11 | C36: -9053.85 | D36: 12852 | E36: 3798.15 | F36: -49.15 | G36: -2942.42 | H36: -964.37 | I36: -339.25 | J36: -392.26 | K36: -2000 | L36: -1935 | M36: -431.4 | N36: =sum(2677.26*2,3229.93) -> 8584.45 | O36: =sum(1677.03,1597.26) -> 3274.29 | P36: =sum(342.06,154.57,342.06,154.57) -> 993.26
A37: 2022 | B37: 12 | C37: -16146.66 | D37: 9407.24 | E37: -6739.42 | F37: -120 | G37: -1110.46 | H37: -849.03 | I37: -573.97 | J37: -56.8 | K37: -10000 | L37: -3040 | M37: -396.4 | N37: =sum(2677.26)*2 -> 5354.52 | O37: =sum(1524.43,1535.03) -> 3059.46 | P37: =sum(342.06,154.57,342.06,154.57) -> 993.26
A38: 2023 | B38: 1 | C38: -5886.78 | D38: 12655.27 | E38: 6768.49 | F38: -20 | G38: -295.51 | H38: -612.07 | I38: -1289.48 | J38: -665.32 | K38: 0 | L38: -2540 | M38: -464.4 | N38: =2677.26*2 -> 5354.52 | O38: =sum(1886.39,2125.84,1798.63) -> 5810.86 | P38: =sum(342.06*3,154.57*3) -> 1489.89
A39: 2023 | B39: 2 | C39: -7471.21 | D39: 8569.45 | E39: 1098.24 | F39: 0 | G39: -677.03 | H39: -1338.47 | I39: -1768.98 | J39: -433.3 | K39: 0 | L39: -2540 | M39: -713.43 | N39: =2677.26*2 -> 5354.52 | O39: =sum(2718.3) -> 2718.3 | P39: =sum(342.06,154.57) -> 496.63
A40: 2023 | B40: 3 | C40: -10331.23 | D40: 11967.09 | E40: 1635.86 | F40: -1914.72 | G40: -345.12 | H40: -3050.02 | I40: -1059.23 | J40: -512.64 | K40: 0 | L40: -2590 | M40: -859.5 | N40: =2677.26*2 -> 5354.52 | O40: =sum(1624.89,1806.27,1846.09) -> 5277.25 | P40: =sum(342.06*3,154.57*2) -> 1335.32
A41: 2023 | B41: 4 | C41: -6071.86 | D41: 14947.84 | E41: 8875.98 | F41: -13.44 | G41: -169.06 | H41: -585.07 | I41: -1250.69 | J41: -833.3 | K41: 0 | L41: -2590 | M41: -630.3 | N41: =sum(2718.98,2722.06) -> 5441.04 | O41: =sum(73.6,2590.06) -> 2663.66 | P41: =sum(3900,2942.64) -> 6842.64 | Q41: 0.5
A42: 2023 | B42: 5 | C42: -4116.19 | D42: 5048.02 | E42: 931.83 | F42: 0 | G42: -12 | H42: -683.69 | I42: -255.38 | J42: -231.32 | K42: 0 | L42: -2590 | M42: -343.8 | N42: =2722.06 -> 2722.06 | O42: =sum(1771.51) -> 1771.51 | P42: =sum(375.41,155.41) -> 530.82 | Q42: 23.63
A43: 2023 | B43: 6 | C43: -8517.79 | D43: 11352.46 | E43: 2834.67 | F43: -41.5 | G43: -535.16 | H43: -1739.75 | I43: -1384.54 | J43: -675.75 | K43: -430 | L43: -2590 | M43: -1121.09 | N43: =2794.07*2 -> 5588.14 | O43: =sum(2113.91,2142.78) -> 4256.69 | P43: =sum(110.41*3,375.41*3) -> 1457.46 | Q43: =sum(49.69,0.48) -> 50.17
A44: 2023 | B44: 7 | C44: -13309.72 | D44: 10376.98 | E44: -2932.74 | F44: -80 | G44: -5493.31 | H44: -2661.45 | I44: -1030.41 | J44: -386.81 | K44: -214.15 | L44: -2985 | M44: -458.59 | N44: =2794.07*2 -> 5588.14 | O44: =sum(1888.3,1867.24) -> 3755.54 | P44: =sum(375.41*2,110.41*2) -> 971.64 | Q44: =sum(61.09,0.57) -> 61.66
A45: 2023 | B45: 8 | C45: -7082.04 | D45: 10836.53 | E45: 3754.49 | F45: -4359.75 | G45: 4327.71 | H45: -961.65 | I45: -1307.77 | J45: -654.53 | K45: -30.55 | L45: -2629 | M45: -1466.5 | N45: =2794.07*2 -> 5588.14 | O45: =sum(2211.12,1994.87) -> 4205.99 | P45: =sum(375.41*2,110.41*2) -> 971.64 | Q45: =sum(70.12,0.64) -> 70.76
A46: 2023 | B46: 9 | C46: -7514.69 | D46: 10501.82 | E46: 2987.13 | F46: -24 | G46: -1683.58 | H46: -466.3 | I46: -1489.12 | J46: -607.4 | K46: 0 | L46: -2629 | M46: -615.29 | N46: =2794.07*2 -> 5588.14 | O46: =sum(2266.96,1595.16) -> 3862.12 | P46: =sum(375.41*2,110.41*2) -> 971.64 | Q46: 79.92
A47: 2023 | B47: 10 | C47: -8817.13 | D47: 11032.25 | E47: 2215.12 | F47: -20 | G47: -2181.3 | H47: -1485.91 | I47: -1517.11 | J47: -733.85 | K47: 0 | L47: -2629 | M47: -249.96 | N47: =3043.41*2 -> 6086.82 | O47: =sum(2116.97,1763.23) -> 3880.2 | P47: =sum(375.41*2,110.41*2) -> 971.64 | Q47: 93.59
A48: 2023 | B48: 11 | C48: -11427.02 | D48: 17470.73 | E48: 6043.71 | F48: -1126.33 | G48: -3385.59 | H48: -1283.8 | I48: -1926.97 | J48: -565.93 | K48: 0 | L48: -2629 | M48: -509.4 | N48: =3041.43*2+3940.7 -> 10023.56 | O48: =sum(1790.93,2240.98,1841.82) -> 5873.73 | P48: =sum(375.41*3,110.41*3) -> 1457.46 | Q48: 115.98
A49: 2023 | B49: 12 | C49: -28649.82 | D49: 10103.49 | E49: -18546.33 | F49: -223.18 | G49: -3822.05 | H49: -565.43 | I49: -1051.2 | J49: -379.22 | K49: -20000 | L49: -2129 | M49: -479.74 | N49: =sum(2776.47,2240.59) -> 5017.06 | O49: =sum(2124,1866.68) -> 3990.68 | P49: =sum(375.41*2,110.41*2) -> 971.64 | Q49: =sum(122.96,1.15) -> 124.11
A50: 2024 | B50: 1 | C50: -11119.65 | D50: 10575.24 | E50: -544.41 | F50: -257.95 | G50: -3513.29 | H50: -724.69 | I50: -1693.19 | J50: -505.66 | K50: -1300 | L50: -2629 | M50: -495.87 | N50: =sum(200,3043.41*2) -> 6286.82 | O50: =sum(2534.19,648.33) -> 3182.52 | P50: =sum(375.41*2,110.41*2) -> 971.64 | Q50: =sum(133.02,1.24) -> 134.26
A51: 2024 | B51: 2 | C51: -7312.46 | D51: 7525.17 | E51: 212.71 | F51: -100 | G51: -322.16 | H51: -953.36 | I51: -1430.25 | J51: -272.75 | K51: -1451.74 | L51: -2529 | M51: -253.2 | N51: =sum(568.94,1501.5,3043.41) -> 5113.85 | O51: =648.33*2 -> 1296.66 | P51: =sum(375.41*2,110.41*2) -> 971.64 | Q51: =sum(141.7,1.32) -> 143.02
A52: 2024 | B52: 3 | C52: -9126.06 | D52: 8490.39 | E52: -635.67 | F52: -2423.12 | G52: -1021.26 | H52: -878.26 | I52: -910.89 | J52: -717.93 | K52: -196 | L52: -2641 | M52: -337.6 | N52: =3043.41*2 -> 6086.82 | O52: =sum(648.33*2) -> 1296.66 | P52: =sum(375.41*2,110.41*2) -> 971.64 | Q52: 135.27
A53: 2024 | B53: 4 | C53: -6446.79 | D53: 8352.56 | E53: 1905.77 | F53: -65.13 | G53: -823.7 | H53: -1059.95 | I53: -1094.51 | J53: -424.9 | K53: 0 | L53: -2641 | M53: -337.6 | N53: =3043.41*2 -> 6086.82 | O53: =sum(684.42*2) -> 1368.84 | P53: =sum(346.53*2,101.92*2) -> 896.9
A54: 2024 | B54: 5 | C54: -7983.29 | D54: 12660.31 | E54: 4677.02 | F54: -31.78 | G54: -2097.2 | H54: -879.95 | I54: -1215.77 | J54: -491.3 | K54: 0 | L54: -2641 | M54: -626.29 | N54: =3043.41*3 -> 9130.23 | O54: =sum(684.42*2,815.89) -> 2184.73 | P54: =sum(346.53*3,101.92*3) -> 1345.35
A55: 2024 | B55: 6 | C55: -5040.56 | D55: 8567.76 | E55: 3527.2 | F55: -22.69 | G55: -634.96 | H55: -507.21 | I55: -815.94 | J55: -551.96 | K55: 0 | L55: -2641 | M55: 133.2 | N55: =3151.01*2 -> 6302.02 | O55: =sum(684.42*2) -> 1368.84 | P55: =sum(346.53*2,101.92*2) -> 896.9
A56: 2024 | B56: 7 | C56: -10938 | D56: 9068.08 | E56: -1869.92 | F56: -27.3 | G56: -2619.91 | H56: -3237.06 | I56: -1474.93 | J56: -261.57 | K56: 0 | L56: -3036 | M56: -281.23 | N56: =3245.01*2 -> 6490.02 | O56: =sum(684.42*2,312.32) -> 1681.16 | P56: =sum(346.53*2,101.92*2) -> 896.9
A57: 2024 | B57: 8 | C57: -5781.3 | D57: 9605.22 | E57: 3823.92 | F57: -22 | G57: -529.98 | H57: -635.39 | I57: -1098.01 | J57: -563.32 | K57: 0 | L57: -2641 | M57: -291.6 | N57: =3245.01*2 -> 6490.02 | O57: =sum(1557.6*2) -> 3115.2
A58: 2024 | B58: 9 | C58: -6120.54 | D58: 9605.22 | E58: 3484.68 | F58: -20 | G58: -482.07 | H58: -1204.66 | I58: -1141.4 | J58: -498.13 | K58: 100 | L58: -2641 | M58: -233.28 | N58: =3245.01*2 -> 6490.02 | O58: =1557.6*2 -> 3115.2
A59: 2024 | B59: 10 | C59: -6570.89 | D59: 14627.4 | E59: 8056.51 | F59: 0 | G59: -1809.57 | H59: -869.32 | I59: -961.93 | J59: -84.95 | K59: 0 | L59: -2641 | M59: -204.12 | N59: =3291.24+3302.3+3361.06 -> 9954.6 | O59: =1557.6*3 -> 4672.8
A60: 2024 | B60: 11 | C60: -8771.89 | D60: 9694.22 | E60: 922.33 | F60: -976.9 | G60: -2463.72 | H60: -666.35 | I60: -1549.13 | J60: -630.21 | K60: 0 | L60: -2141 | M60: -344.58 | N60: =3331.68*2 -> 6663.36 | O60: =sum(100.45,8.2,1557.6,12.3,1246.28) -> 2924.83 | P60: 106.03
A61: 2024 | B61: 12 | C61: -13691.1 | D61: 10219.83 | E61: -3471.27 | F61: -100 | G61: -1126.23 | H61: -1638.81 | I61: -1339.21 | J61: -579.6 | K61: -5000 | L61: -3641 | M61: -266.25 | N61: =4407.56+3515.61 -> 7923.17 | O61: =28.7+2239.26+28.7 -> 2296.66
A62: 2025 | B62: 1 | C62: -11256.84 | D62: 9211.6 | E62: -2045.24 | F62: -30 | G62: -378.82 | H62: -417.78 | I62: -1829.55 | J62: -598.35 | K62: -5000 | L62: -2641 | M62: -361.34 | N62: =3515.61*2 -> 7031.22 | O62: =28.7*2+2122.98 -> 2180.38
A63: 2025 | B63: 2 | C63: -6822.81 | D63: 8009.63 | E63: 1186.82 | F63: -30 | G63: -606.55 | H63: -1538.9 | I63: -1308.15 | J63: -376.93 | K63: -38 | L63: -2641 | M63: -283.28 | N63: =3515.61+3647.34 -> 7162.95 | O63: =sum(28.7*2,301.56,487.72) -> 846.68
A64: 2025 | B64: 3 | C64: -12781.32 | D64: 8546.99 | E64: -4234.33 | F64: 0 | G64: -114.92 | H64: -3222.92 | I64: -1230.51 | J64: -269.92 | K64: -5000 | L64: -2641 | M64: -302.05 | N64: =3515.61*2 -> 7031.22 | O64: =384.17+28.7+101.95+28.7+203.91 -> 747.43 | P64: 768.34
A65: 2025 | B65: 4 | C65: -6219.8 | D65: 11448.89 | E65: 5229.09 | F65: -5.6 | G65: -615.04 | H65: -707.91 | I65: -1554.5 | J65: -412.47 | K65: 0 | L65: -2641 | M65: -283.28 | N65: =3515.61*3 -> 10546.83 | O65: =28.7*2+152.63 -> 210.03 | P65: =sum(454.85,113.71,123.47) -> 692.03
A66: 2025 | B66: 5 | C66: -6466.07 | D66: 8706.82 | E66: 2240.75 | F66: -90 | G66: -386.37 | H66: -1044.16 | I66: -1451.82 | J66: -529.44 | K66: 0 | L66: -2641 | M66: -323.28 | N66: =3515.61*2 -> 7031.22 | O66: =28.7*3+101.95*2+210.03 -> 500.03 | P66: =384.17+791.4 -> 1175.57
A67: 2025 | B67: 6 | C67: -8757.38 | D67: 8105.15 | E67: -652.23 | F67: -20 | G67: -2442.25 | H67: -1709.96 | I67: -1289.41 | J67: -371.48 | K67: 0 | L67: -2641 | M67: -283.28 | N67: =3641.58*2 -> 7283.16 | O67: =28.7*2+157.22 -> 214.62 | P67: 607.37
A68: 2025 | B68: 7 | C68: -7019.42 | D68: 8059.89 | E68: 1040.47 | F68: -20 | G68: -881.4 | H68: -1062.7 | I68: -1374.21 | J68: -587.86 | K68: 0 | L68: -2651 | M68: -442.25 | N68: =3641.5*2 -> 7283 | O68: =157.22+12.3 -> 169.52 | P68: 607.37
A69: 2025 | B69: 8 | C69: -5931.69 | D69: 11027.15 | E69: 5095.46 | F69: 0 | G69: 2078.14 | H69: -1929.22 | I69: -1432.11 | J69: -664.85 | K69: 0 | L69: -3410 | M69: -573.65 | N69: =3641.58*2 -> 7283.16 | O69: =43.88+4+2826.84+164.24+69.58 -> 3108.54 | P69: 635.45
A70: 2025 | B70: 9 | C70: -12784.76 | D70: 9801.16 | E70: -2983.6 | F70: -14 | G70: -5594.8 | H70: -1229.71 | I70: -1296.25 | J70: -709.88 | K70: 0 | L70: -3410 | M70: -530.12 | N70: =3641.58*2 -> 7283.16 | O70: =342.67+171.34 -> 514.01 | P70: =1342.35+661.64 -> 2003.99
A71: 2025 | B71: 10 | C71: -7441.09 | D71: 13473.54 | E71: 6032.45 | F71: -236.04 | G71: -1210.76 | H71: -1082.18 | I71: -809.11 | J71: -116.2 | K71: 0 | L71: -3410 | M71: -576.8 | N71: =3641.6*3 -> 10924.8 | O71: =181.41+170.76+171.34 -> 523.51 | P71: =701.95+661.64+661.64 -> 2025.23
A72: 2025 | B72: 11 | C72: -9227.8 | D72: 9953.6 | E72: 725.8 | F72: -1597.13 | G72: -1114.86 | H72: -1061.37 | I72: -978.5 | J72: -562.08 | K72: 0 | L72: -3410 | M72: -503.86 | N72: =3641.58*2 -> 7283.16 | O72: =355.36+1322.59 -> 1677.95 | P72: 992.49
A73: 2025 | B73: 12 | C73: -5067.88 | D73: 9595.61 | E73: 4527.73 | F73: -14.97 | G73: -1527.35 | H73: -1532.21 | I73: -1276.8 | J73: -473.25 | K73: 0 | L73: 0 | M73: -243.3 | N73: =4697.65+3731.41 -> 8429.06 | O73: 1166.55

Sheet Pivot
N1: Transport% | O1: Living% | P1: Bill% | Q1: Groceries% | R1: Dine% | S1: RMIT% | T1: Mortgage% | U1: Childcare%
N2: =F2/$D2 -> 0.03551815 | O2: =G2/$D2 -> 0.54085106 | P2: =H2/$D2 -> 0.21066329 | Q2: =I2/$D2 -> 0 | R2: =J2/$D2 -> 0.024811963 | S2: =K2/$D2 -> 0.18815554 | T2: =L2/$D2 -> 0 | U2: =M2/$D2 -> 0
N3: =F3/$D3 -> 0.06941561 | O3: =G3/$D3 -> 0.33907113 | P3: =H3/$D3 -> 0.24693532 | Q3: =I3/$D3 -> 0 | R3: =J3/$D3 -> 0.014058863 | S3: =K3/$D3 -> 0.23842151 | T3: =L3/$D3 -> 0.12766978 | U3: =M3/$D3 -> 0
N4: =F4/$D4 -> 0.017516234 | O4: =G4/$D4 -> 0.24535397 | P4: =H4/$D4 -> 0.14996336 | Q4: =I4/$D4 -> 0.090011997 | R4: =J4/$D4 -> 0.047912244 | S4: =K4/$D4 -> 0.26734462 | T4: =L4/$D4 -> 0.24115905 | U4: =M4/$D4 -> 0.041452264
N5: =F5/$D5 -> 0.065631012 | O5: =G5/$D5 -> 0.11973608 | P5: =H5/$D5 -> 0.1294815 | Q5: =I5/$D5 -> 0.12861964 | R5: =J5/$D5 -> 0.056037108 | S5: =K5/$D5 -> 0.17345205 | T5: =L5/$D5 -> 0.26066425 | U5: =M5/$D5 -> 0.066378356
N6: =F6/$D6 -> 0.04091776 | O6: =G6/$D6 -> 0.17637618 | P6: =H6/$D6 -> 0.13402094 | Q6: =I6/$D6 -> 0.14888557 | R6: =J6/$D6 -> 0.056442237 | S6: =K6/$D6 -> 0.079348223 | T6: =L6/$D6 -> 0.32823225 | U6: =M6/$D6 -> 0.03577684
N7: =F7/$D7 -> 0.020623419 | O7: =G7/$D7 -> 0.12823595 | P7: =H7/$D7 -> 0.16576008 | Q7: =I7/$D7 -> 0.15866324 | R7: =J7/$D7 -> 0.056853964 | S7: =K7/$D7 -> 0.10060449 | T7: =L7/$D7 -> 0.32208871 | U7: =M7/$D7 -> 0.047170155

Sheet 324
A1: Equity Date | B1: Estimated Home Value (AUD) | C1: Outstanding Mortgage (AUD) | D1: Home Equity (AUD)
A2: 44384 | B2: 838000 | C2: -502411.8 | D2: =B2+C2 -> 335588.2
A3: 44457 | B3: 865000 | C3: -502411.8 | D3: =B3+C3 -> 362588.2
A4: 45566 | B4: 989000 | C4: -502411.8 | D4: =B4+C4 -> 486588.2
A5: 45292 | B5: 970000 | C5: -502411.8 | D5: =B5+C5 -> 467588.2
A6: 45717 | B6: 970000 | C6: -502411.8 | D6: =B6+C6 -> 467588.2
A7: 45753 | B7: 972000 | C7: -441336.64 | D7: =B7+C7 -> 530663.36
A8: 45784 | B8: 978000 | C8: -441336.64 | D8: =B8+C8 -> 536663.36
A9: 45920 | B9: 908779 | C9: -434869 | D9: =B9+C9 -> 473910
A10: 45969 | B10: 974000 | C10: -434869 | D10: =B10+C10 -> 539131
A28: Expense log
B29: 44384 | C29: -502411.8 | D29: Mortgage
B30: 44287 | C30: -81000 | D30: Deposit
B31: 44356 | C31: -900 | D31: TV + Washing machine
B32: 44358 | C32: =-sum(56.7,76.94) -> -133.64
B33: 44363 | C33: -472.5
B34: 44379 | C34: -674
B35: 44380 | C35: -719
B36: 44384 | C36: -1333
B37: 44389 | C37: -169.95
B38: 44390 | C38: -13.99
B39: 44391 | C39: -129
B40: 44392 | C40: =-sum(233,296) -> -529
B41: 44395 | C41: -506
